Workbook

Sheet README
A1: Inventory Policy Calculator — ABC-XYZ, Safety Stock, Reorder Point & EOQ
A2: Segments 500 real SKUs by value and demand predictability, then sets safety stock, reorder point and order quantity per SKU and prices the cost of higher service.
A4: 1. Business scenario
A5: Role | B5: Junior inventory analyst, UK-based online retailer of all-occasion gift-ware selling largely to wholesale customers.
A6: The ask | B6: "We have too much cash tied up in stock that doesn't sell, and we keep running out of our best sellers. Build a stocking policy for every SKU — how much to hold and when to reorder — and show me what it costs to raise our service level." — Operations Director
A7: Deliverables | B7: Segment SKUs (ABC-XYZ) · safety stock, reorder point and EOQ per SKU · flag reorder-now and excess SKUs · service level vs. inventory cost trade-off · policy per segment
A9: 2. Data source
A10: Dataset | B10: Chen, D. (2012). Online Retail II [Dataset]. UCI Machine Learning Repository. https://doi.org/10.24432/C5CG6D
A11: Licence | B11: CC BY 4.0 — https://archive.ics.uci.edu/dataset/502/online+retail+ii
A12: Scope used | B12: 52 complete weeks (6 Dec 2010 – 4 Dec 2011), top 500 SKUs by revenue (67.5% of product revenue). Currency: GBP (£), as in the source.
A13: NOT in the data | B13: Unit cost, supplier lead time and on-hand stock. These are ASSUMED or SIMULATED and labelled everywhere they appear (see section 6).
A15: 3. How to use this file
A16: Tabs in order | B16: README → Assumptions → Weekly_Demand → SKU_Policy → ABC_XYZ_Matrix → Service_Level_Scenario → Summary → Spot_Check → Data_Prep
A17: Paste new data | B17: Only into Weekly_Demand, rows 5–504: A–B (SKU, Description), F (On Hand snapshot), G–BF (W1–W52) and BG (median price). Columns C–E are formulas. Row 5 is the format example. Data comes from the Power Query steps on the Data_Prep tab.
A18: Safe to edit | B18: Orange text on light-yellow fill: Assumptions inputs (parameters, margin, lead-time shock, lead-time buckets, category keywords), Service_Level_Scenario levels and extra lead-time weeks, Spot_Check SKU codes.
A19: Do not overwrite | B19: Everything in black or green text — they are formulas. SKU_Policy, ABC_XYZ_Matrix and Summary update automatically.
A20: Scenario test | B20: Set Assumptions!B19 (lead-time shock) to 2 → watch Summary safety stock value and SKUs to reorder jump. Change A service level to 99% → see the cost.
A22: 4. Colour legend
A23: Orange text | B23: Input or assumption you can change
A24: Black text | B24: Formula — do not overwrite
A25: Green text | B25: Formula pulling a value from another tab
A26: Light-yellow fill | B26: Key assumption to review
A27: Red status | B27: Below Safety Stock — stock-out risk, expedite
A28: Amber status | B28: Reorder Now — at/below reorder point
A29: Green status | B29: Healthy
A30: Purple status | B30: Excess — above reorder point + EOQ, cash tied up
A32: 5. Key formulas in plain English
A33: Metric | B33: Formula | C33: Business meaning
A34: CV (coefficient of variation) | B34: Std Dev of weekly demand ÷ Avg weekly demand | C34: How unpredictable demand is, independent of volume — 0.3 is steady, 1.5 is lumpy.
A35: ABC class | B35: Rank SKUs by annual consumption value (demand × unit cost); cumulative share ≤ 80% → A, ≤ 95% → B, else C | C35: Where the money is — A items deserve the most planner attention.
A36: XYZ class | B36: CV ≤ 0.5 → X, ≤ 1.0 → Y, else Z | C36: How forecastable demand is — X can be automated, Z needs human judgement.
A37: Z-score | B37: NORMSINV(target service level) | C37: How many standard deviations of buffer are needed to hit the service level (95% → 1.645).
A38: Safety stock | B38: Z × Std Dev weekly demand × √(Lead time in weeks), rounded up | C38: Buffer stock that protects against demand swings while waiting for the supplier.
A39: Reorder point (ROP) | B39: Avg weekly demand × Lead time + Safety stock, rounded up | C39: When stock falls to this level, place an order.
A40: EOQ | B40: √(2 × Annual demand × Ordering cost ÷ (Holding cost % × Unit cost)) | C40: The order size that minimises the combined cost of ordering and holding stock.
A41: Stock status | B41: On Hand ≤ SS → Below Safety Stock; ≤ ROP → Reorder Now; > ROP + EOQ → Excess; else Healthy | C41: The planner action list.
A42: Inventory turns / days on hand | B42: Annual consumption value ÷ On-hand value; 365 ÷ turns | C42: How fast stock converts to sales; lower days = less cash tied up.
A44: 6. Assumptions (labelled — change on the Assumptions tab)
A45: Unit Cost — ASSUMPTION | B45: Median selling price × (1 − 40% gross margin) = 60% of price. Margin is Assumptions!B18.
A46: Lead Time — SIMULATED | B46: 2, 4, 6 or 8 weeks, picked by formula from the StockCode (MOD of first 5 digits, 4) using the bucket table on Assumptions. Reproducible, not random. Optional shock in Assumptions!B19.
A47: On Hand — SIMULATED | B47: Deterministic snapshot = Avg weekly demand × weeks of cover (1–4, 6–16 or 26–52 weeks chosen by a StockCode hash) to create a realistic mix of under-, normal and over-stocked SKUs. Rule on Assumptions tab.
A48: Ordering / holding cost — ASSUMPTION | B48: £50 per order; 25% of unit cost per year.
A49: Category — DERIVED | B49: Formula on Description using the keyword table on Assumptions (whole words): BAG(S) → Bags; CANDLE(S)/LIGHT(S) → Lighting; MUG(S)/CAKE(S)/CAKESTAND/TIN(S) → Kitchen; CARD(S) → Cards/Gifts; else Other.
A51: 7. Model limitations
A52: Normal demand | B52: Safety stock assumes weekly demand is roughly normally distributed. This is weak for lumpy Z-class items (most of this range, because wholesale orders are large and irregular) — treat their safety stock as indicative and review manually.
A53: Fixed lead time | B53: Lead time is a single fixed number per SKU. A fuller model adds lead-time variability: SS = Z × √(LT × σd² + d̄² × σLT²).
A54: Simulated inputs | B54: Unit cost, lead time and on-hand figures are simulated assumptions, not observed data. The METHOD is real; £ values and stock-status counts illustrate it.
A55: History = forecast | B55: Uses the last 52 weeks as the demand estimate (no trend or seasonality forecast). Gift-ware has a strong Q4 peak, so a seasonal policy would hold more stock before Christmas.
A56: Scope | B56: Top 500 SKUs by revenue only; the long tail of ~3,275 SKUs is excluded from this workbook. ABC classes are relative to these 500.
A57: Sample std dev | B57: STDEV (sample, n−1) over 52 weeks including zero-sales weeks.
A59: Data preparation (Power Query ribbon steps and row counts): Data_Prep tab. Reconciliation of 3 SKUs: Spot_Check tab.

Sheet Assumptions
A1: Assumptions & Parameters
A2: Cells with orange text on light-yellow fill are inputs. Every formula in the workbook points to these cells; no numbers are typed inside formulas.
A3: Parameter | B3: Value | C3: Unit | D3: What it drives / notes
A4: Ordering cost per order | B4: 50 | C4: £ per order | D4: EOQ. Assumption: admin + receiving cost of placing one purchase order.
A5: Annual holding cost % | B5: 0.25 | C5: % of unit cost per year | D5: EOQ. Assumption: cost of capital, storage, insurance, obsolescence.
A6: Weeks per year | B6: 52 | C6: weeks | D6: Avg Weekly Demand = Annual Demand ÷ this. Matches the 52 weekly columns.
A7: ABC cut-off A — cumulative value share | B7: 0.8 | C7: fraction | D7: SKUs whose cumulative value share ≤ this are class A.
A8: ABC cut-off B — cumulative value share | B8: 0.95 | C8: fraction | D8: SKUs above the A cut-off and ≤ this are class B; the rest are C.
A9: XYZ cut-off X — max coefficient of variation | B9: 0.5 | C9: CV | D9: CV ≤ this → X (steady demand).
A10: XYZ cut-off Y — max coefficient of variation | B10: 1 | C10: CV | D10: CV ≤ this → Y (variable); above → Z (lumpy).
A11: Target service level — A items | B11: 0.98 | C11: cycle service level | D11: Probability of not stocking out during a replenishment cycle.
A12: Target service level — B items | B12: 0.95 | C12: cycle service level
A13: Target service level — C items | B13: 0.9 | C13: cycle service level
A14: Days per year | B14: 365 | C14: days | D14: Days on Hand = this ÷ Inventory Turns (Summary tab).
A16: Assumptions for data the source does not contain (cost, lead time, stock)
A17: Parameter | B17: Value | C17: Unit | D17: What it drives / notes
A18: ASSUMPTION — Gross margin used to derive unit cost | B18: 0.4 | C18: fraction of selling price | D18: Unit Cost = Median selling price × (1 − this). 40% margin → cost = 60% of price. Drives Weekly_Demand column D and every £ figure.
A19: ASSUMPTION — Lead-time shock (weeks added to every SKU) | B19: 0 | C19: weeks | D19: Supplier-delay stress test (tariff changes, border holds, port congestion). 0 = base case. Added in SKU_Policy column D.
A21: SIMULATED — Lead time buckets (weeks)
A22: Bucket | B22: Lead time | C22: Unit | D22: Rule
A23: Bucket 1 (MOD of first 5 digits of StockCode, 4 = 0) | B23: 2 | C23: weeks | D23: Weekly_Demand!E: =INDEX(Assumptions!$B$23:$B$26, MOD(VALUE(LEFT(SKU,5)),4)+1). Same result every time the file is opened.
A24: Bucket 2 (MOD of first 5 digits of StockCode, 4 = 1) | B24: 4 | C24: weeks
A25: Bucket 3 (MOD of first 5 digits of StockCode, 4 = 2) | B25: 6 | C25: weeks
A26: Bucket 4 (MOD of first 5 digits of StockCode, 4 = 3) | B26: 8 | C26: weeks
A28: SIMULATED — How the On Hand snapshot was created
A29: A stock snapshot should not move when demand history changes, so On Hand was created once with the Excel formula below (row 5 example), then Copy → Paste Values into Weekly_Demand column F:
A30: Formula (row 5): =ROUND(AVERAGE(G5:BF5) * IF(MOD(VALUE(LEFT(A5,5))*37+LEN(A5)*11,100)<20, 1+MOD(MOD(VALUE(LEFT(A5,5))*37+LEN(A5)*11,100),4), IF(MOD(VALUE(LEFT(A5,5))*37+LEN(A5)*11,100)<75, 6+MOD(MOD(VALUE(LEFT(A5,5))*37+LEN(A5)*11,100),11), 26+MOD(MOD(VALUE(LEFT(A5,5))*37+LEN(A5)*11,100),27))), 0)
A31: In words: a code-based number h (0–99) sets weeks of cover — h below 20 → 1–4 weeks (understocked), 20–74 → 6–16 weeks (normal), 75+ → 26–52 weeks (overstocked). On Hand = average weekly demand × weeks of cover. No RAND(), so anyone can reproduce it.
A33: Service level lookup (formula — used by SKU_Policy)
A34: ABC Class | B34: Target Service Level
A35: A | B35: =$B$11 -> 0.98
A36: B | B36: =$B$12 -> 0.95
A37: C | B37: =$B$13 -> 0.9
A39: Category keyword table (checked top to bottom — first keyword found in the Description wins)
A40: Keyword (whole word) | B40: Category
A41: BAG | B41: Bags
A42: BAGS | B42: Bags
A43: CANDLE | B43: Lighting
A44: CANDLES | B44: Lighting
A45: LIGHT | B45: Lighting
A46: LIGHTS | B46: Lighting
A47: MUG | B47: Kitchen
A48: MUGS | B48: Kitchen
A49: CAKE | B49: Kitchen
A50: CAKES | B50: Kitchen
A51: CAKESTAND | B51: Kitchen
... A55: CARDS | B55: Cards/Gifts
A56: To add a keyword, insert a row INSIDE this table (above the last row) so the formula range expands. Anything with no match = "Other".

Sheet Weekly_Demand
A1: Weekly_Demand — input data (the only tab where new data is pasted)
A2: Paste values from row 5: A SKU · B Description · G:BF weekly units W1–W52 · BG Median Sell Price · F On Hand snapshot. Columns C, D, E are formulas (gold headers) — do not paste over them. Row 5 is the format example. Capacity 500 SKUs (rows 5–504).
F3: Week starting (Mon) → | G3: 40518 | H3: =G3+7 -> 40525 | I3: =H3+7 -> 40532 | J3: =I3+7 -> 40539 | K3: =J3+7 -> 40546 | L3: =K3+7 -> 40553 | M3: =L3+7 -> 40560 | N3: =M3+7 -> 40567 | O3: =N3+7 -> 40574 | ... BF3: =BE3+7 -> 40875
A4: SKU (StockCode) | B4: Description | C4: Category (keyword formula) | D4: Unit Cost (£) ASSUMPTION | E4: Lead Time (weeks) SIMULATED | F4: On Hand (simulated) units | G4: W1 | H4: W2 | I4: W3 | J4: W4 | K4: W5 | L4: W6 | M4: W7 | N4: W8 | O4: W9 | P4: W10 | Q4: W11 | R4: W12 | S4: W13 | T4: W14 | U4: W15 | V4: W16 | W4: W17 | X4: W18 | Y4: W19 | Z4: W20 | AA4: W21 | AB4: W22 | AC4: W23 | AD4: W24 | AE4: W25 | AF4: W26 | AG4: W27 | AH4: W28 | AI4: W29 | AJ4: W30 | AK4: W31 | AL4: W32 | AM4: W33 | AN4: W34 | AO4: W35 | AP4: W36 | AQ4: W37 | AR4: W38 | AS4: W39 | AT4: W40 | AU4: W41 | AV4: W42 | AW4: W43 | AX4: W44 | AY4: W45 | AZ4: W46 | BA4: W47 | BB4: W48 | BC4: W49 | BD4: W50 | BE4: W51 | BF4: W52 | BG4: Median Sell Price (£)
A5: 22423 | B5: REGENCY CAKESTAND 3 TIER | C5: =IF(A5="","",IFERROR(INDEX(Assumptions!$B$41:$B$55,MATCH(TRUE(),INDEX(ISNUMBER(SEARCH(" "&Assumptions!$A$41:$A$55&" "," "&SUBSTITUTE(SUBSTITUTE(SUBSTITUTE(SUBSTITUTE(B5,"-"," "),","," "),"/"," "),"."," ")&" ")),0),0)),"Other")) -> Kitchen | D5: =IF(A5="","",BG5*(1-Assumptions!$B$18)) -> 7.65 | E5: =IF(A5="","",INDEX(Assumptions!$B$23:$B$26,MOD(VALUE(LEFT(A5,5)),4)+1)) -> 8 | F5: 743 | G5: 851 | H5: 442 | I5: 178 | J5: 0 | K5: 251 | L5: 407 | M5: 139 | N5: 231 | O5: 150 | P5: 139 | Q5: 400 | R5: 204 | S5: 349 | T5: 190 | U5: 308 | V5: 329 | W5: 334 | X5: 282 | Y5: 366 | Z5: 186 | AA5: 325 | AB5: 171 | AC5: 366 | AD5: 307 | AE5: 169 | AF5: 263 | AG5: 208 | AH5: 174 | AI5: 143 | AJ5: 85 | AK5: 131 | AL5: 292 | AM5: 341 | AN5: 342 | AO5: 180 | AP5: 178 | AQ5: 210 | AR5: 242 | AS5: 147 | AT5: 150 | AU5: 219 | AV5: 147 | AW5: 149 | AX5: 409 | AY5: 214 | AZ5: 268 | BA5: 135 | BB5: 279 | BC5: 169 | BD5: 235 | BE5: 261 | BF5: 236 | BG5: 12.75 | BH5: ← format example: SKU as text, whole-number units, price in £
A6: 85123A | B6: WHITE HANGING HEART T-LIGHT HOLDER | C6: =IF(A6="","",IFERROR(INDEX(Assumptions!$B$41:$B$55,MATCH(TRUE(),INDEX(ISNUMBER(SEARCH(" "&Assumptions!$A$41:$A$55&" "," "&SUBSTITUTE(SUBSTITUTE(SUBSTITUTE(SUBSTITUTE(B6,"-"," "),","," "),"/"," "),"."," ")&" ")),0),0)),"Other")) -> Lighting | D6: =IF(A6="","",BG6*(1-Assumptions!$B$18)) -> 1.77 | E6: =IF(A6="","",INDEX(Assumptions!$B$23:$B$26,MOD(VALUE(LEFT(A6,5)),4)+1)) -> 8 | F6: 1395 | G6: 1122 | H6: 1529 | I6: 198 | J6: 0 | K6: 973 | L6: 3329 | M6: 662 | N6: 546 | O6: 588 | P6: 517 | Q6: 365 | R6: 401 | S6: 380 | T6: 454 | U6: 464 | V6: 365 | W6: 582 | X6: 374 | Y6: 474 | Z6: 2422 | AA6: 375 | AB6: 1144 | AC6: 892 | AD6: 794 | AE6: 1026 | AF6: 629 | AG6: 390 | AH6: 391 | AI6: 236 | AJ6: 258 | AK6: 264 | AL6: 1198 | AM6: 729 | AN6: 780 | AO6: 441 | AP6: 477 | AQ6: 297 | AR6: 775 | AS6: 396 | AT6: 449 | AU6: 663 | AV6: 710 | AW6: 408 | AX6: 165 | AY6: 683 | AZ6: 234 | BA6: 447 | BB6: 1707 | BC6: 594 | BD6: 1326 | BE6: 904 | BF6: 731 | BG6: 2.95
A7: 47566 | B7: PARTY BUNTING | C7: =IF(A7="","",IFERROR(INDEX(Assumptions!$B$41:$B$55,MATCH(TRUE(),INDEX(ISNUMBER(SEARCH(" "&Assumptions!$A$41:$A$55&" "," "&SUBSTITUTE(SUBSTITUTE(SUBSTITUTE(SUBSTITUTE(B7,"-"," "),","," "),"/"," "),"."," ")&" ")),0),0)),"Other")) -> Other | D7: =IF(A7="","",BG7*(1-Assumptions!$B$18)) -> 2.97 | E7: =IF(A7="","",INDEX(Assumptions!$B$23:$B$26,MOD(VALUE(LEFT(A7,5)),4)+1)) -> 6 | F7: 14706 | G7: 165 | H7: 29 | I7: 24 | J7: 0 | K7: 145 | L7: 85 | M7: 69 | N7: 171 | O7: 232 | P7: 292 | Q7: 189 | R7: 157 | S7: 255 | T7: 205 | U7: 606 | V7: 325 | W7: 376 | X7: 460 | Y7: 542 | Z7: 648 | AA7: 276 | AB7: 984 | AC7: 756 | AD7: 754 | AE7: 839 | AF7: 434 | AG7: 663 | AH7: 507 | AI7: 598 | AJ7: 276 | AK7: 901 | AL7: 354 | AM7: 935 | AN7: 520 | AO7: 431 | AP7: 330 | AQ7: 402 | AR7: 471 | AS7: 207 | AT7: 300 | AU7: 334 | AV7: 158 | AW7: 209 | AX7: 183 | AY7: 106 | AZ7: 211 | BA7: 78 | BB7: 102 | BC7: 135 | BD7: 218 | BE7: 455 | BF7: 105 | BG7: 4.95
A8: 85099B | B8: JUMBO BAG RED RETROSPOT | C8: =IF(A8="","",IFERROR(INDEX(Assumptions!$B$41:$B$55,MATCH(TRUE(),INDEX(ISNUMBER(SEARCH(" "&Assumptions!$A$41:$A$55&" "," "&SUBSTITUTE(SUBSTITUTE(SUBSTITUTE(SUBSTITUTE(B8,"-"," "),","," "),"/"," "),"."," ")&" ")),0),0)),"Other")) -> Bags | D8: =IF(A8="","",BG8*(1-Assumptions!$B$18)) -> 1.248 | E8: =IF(A8="","",INDEX(Assumptions!$B$23:$B$26,MOD(VALUE(LEFT(A8,5)),4)+1)) -> 8 | F8: 11833 | G8: 852 | H8: 427 | I8: 180 | J8: 0 | K8: 1374 | L8: 225 | M8: 594 | N8: 502 | O8: 965 | P8: 288 | Q8: 985 | R8: 810 | S8: 624 | T8: 738 | U8: 1546 | V8: 1379 | W8: 1103 | X8: 975 | Y8: 616 | Z8: 549 | AA8: 385 | AB8: 380 | AC8: 1206 | AD8: 978 | AE8: 933 | AF8: 273 | AG8: 883 | AH8: 959 | AI8: 841 | AJ8: 815 | AK8: 1364 | AL8: 431 | AM8: 733 | AN8: 540 | AO8: 1050 | AP8: 1373 | AQ8: 1356 | AR8: 1518 | AS8: 717 | AT8: 556 | AU8: 743 | AV8: 1667 | AW8: 929 | AX8: 2709 | AY8: 947 | AZ8: 1045 | BA8: 600 | BB8: 1063 | BC8: 2200 | BD8: 1602 | BE8: 753 | BF8: 1050 | BG8: 2.08
A9: 23084 | B9: RABBIT NIGHT LIGHT | C9: =IF(A9="","",IFERROR(INDEX(Assumptions!$B$41:$B$55,MATCH(TRUE(),INDEX(ISNUMBER(SEARCH(" "&Assumptions!$A$41:$A$55&" "," "&SUBSTITUTE(SUBSTITUTE(SUBSTITUTE(SUBSTITUTE(B9,"-"," "),","," "),"/"," "),"."," ")&" ")),0),0)),"Other")) -> Lighting | D9: =IF(A9="","",BG9*(1-Assumptions!$B$18)) -> 1.248 | E9: =IF(A9="","",INDEX(Assumptions!$B$23:$B$26,MOD(VALUE(LEFT(A9,5)),4)+1)) -> 2 | F9: 7426 | G9: 0 | H9: 0 | I9: 0 | J9: 0 | K9: 0 | L9: 0 | M9: 0 | N9: 0 | O9: 0 | P9: 0 | Q9: 0 | R9: 0 | S9: 0 | T9: 0 | U9: 0 | V9: 0 | W9: 0 | X9: 0 | Y9: 0 | Z9: 0 | AA9: 0 | AB9: 0 | AC9: 344 | AD9: 256 | AE9: 454 | AF9: 135 | AG9: 199 | AH9: 642 | AI9: 651 | AJ9: 174 | AK9: 140 | AL9: 128 | AM9: 2 | AN9: 13 | AO9: 6 | AP9: 10 | AQ9: 1 | AR9: 768 | AS9: 1161 | AT9: 10 | AU9: 13 | AV9: 35 | AW9: 58 | AX9: 373 | AY9: 3 | AZ9: 14 | BA9: 5593 | BB9: 2672 | BC9: 2646 | BD9: 4279 | BE9: 2343 | BF9: 4460 | BG9: 2.08
A10: 22086 | B10: PAPER CHAIN KIT 50'S CHRISTMAS | C10: =IF(A10="","",IFERROR(INDEX(Assumptions!$B$41:$B$55,MATCH(TRUE(),INDEX(ISNUMBER(SEARCH(" "&Assumptions!$A$41:$A$55&" "," "&SUBSTITUTE(SUBSTITUTE(SUBSTITUTE(SUBSTITUTE(B10,"-"," "),","," "),"/"," "),"."," ")&" ")),0),0)),"Other")) -> Other | D10: =IF(A10="","",BG10*(1-Assumptions!$B$18)) -> 1.77 | E10: =IF(A10="","",INDEX(Assumptions!$B$23:$B$26,MOD(VALUE(LEFT(A10,5)),4)+1)) -> 6 | F10: 3304 | G10: 1055 | H10: 597 | I10: 125 | J10: 0 | K10: 16 | L10: 6 | M10: 2 | N10: 0 | O10: 0 | P10: 0 | Q10: 2 | R10: 2 | S10: 45 | T10: 1 | U10: 0 | V10: 42 | W10: 3 | X10: 9 | Y10: 0 | Z10: 1 | AA10: 0 | AB10: 4 | AC10: 13 | AD10: 0 | AE10: 0 | AF10: 0 | AG10: 2 | AH10: 1 | AI10: 6 | AJ10: 365 | AK10: 18 | AL10: 16 | AM10: 32 | AN10: 287 | AO10: 281 | AP10: 22 | AQ10: 36 | AR10: 28 | AS10: 192 | AT10: 495 | AU10: 601 | AV10: 602 | AW10: 359 | AX10: 977 | AY10: 819 | AZ10: 756 | BA10: 764 | BB10: 1745 | BC10: 1436 | BD10: 2161 | BE10: 1692 | BF10: 1564 | BG10: 2.95
A11: 84879 | B11: ASSORTED COLOUR BIRD ORNAMENT | C11: =IF(A11="","",IFERROR(INDEX(Assumptions!$B$41:$B$55,MATCH(TRUE(),INDEX(ISNUMBER(SEARCH(" "&Assumptions!$A$41:$A$55&" "," "&SUBSTITUTE(SUBSTITUTE(SUBSTITUTE(SUBSTITUTE(B11,"-"," "),","," "),"/"," "),"."," ")&" ")),0),0)),"Other")) -> Other | D11: =IF(A11="","",BG11*(1-Assumptions!$B$18)) -> 1.014 | E11: =IF(A11="","",INDEX(Assumptions!$B$23:$B$26,MOD(VALUE(LEFT(A11,5)),4)+1)) -> 8 | F11: 33543 | G11: 789 | H11: 638 | I11: 40 | J11: 0 | K11: 480 | L11: 442 | M11: 139 | N11: 344 | O11: 937 | P11: 160 | Q11: 588 | R11: 328 | S11: 213 | T11: 642 | U11: 968 | V11: 391 | W11: 585 | X11: 753 | Y11: 815 | Z11: 612 | AA11: 264 | AB11: 594 | AC11: 1201 | AD11: 595 | AE11: 565 | AF11: 384 | AG11: 292 | AH11: 446 | AI11: 270 | AJ11: 292 | AK11: 460 | AL11: 372 | AM11: 519 | AN11: 478 | AO11: 3800 | AP11: 1323 | AQ11: 556 | AR11: 850 | AS11: 216 | AT11: 488 | AU11: 908 | AV11: 701 | AW11: 799 | AX11: 589 | AY11: 420 | AZ11: 829 | BA11: 778 | BB11: 968 | BC11: 1748 | BD11: 1326 | BE11: 1037 | BF11: 953 | BG11: 1.69
A12: 22502 | B12: PICNIC BASKET WICKER SMALL | C12: =IF(A12="","",IFERROR(INDEX(Assumptions!$B$41:$B$55,MATCH(TRUE(),INDEX(ISNUMBER(SEARCH(" "&Assumptions!$A$41:$A$55&" "," "&SUBSTITUTE(SUBSTITUTE(SUBSTITUTE(SUBSTITUTE(B12,"-"," "),","," "),"/"," "),"."," ")&" ")),0),0)),"Other")) -> Other | D12: =IF(A12="","",BG12*(1-Assumptions!$B$18)) -> 3.57 | E12: =IF(A12="","",INDEX(Assumptions!$B$23:$B$26,MOD(VALUE(LEFT(A12,5)),4)+1)) -> 6 | F12: 468 | G12: 40 | H12: 59 | I12: 10 | J12: 0 | K12: 12 | L12: 27 | M12: 28 | N12: 153 | O12: 46 | P12: 24 | Q12: 48 | R12: 72 | S12: 45 | T12: 138 | U12: 27 | V12: 59 | W12: 51 | X12: 64 | Y12: 96 | Z12: 54 | AA12: 47 | AB12: 160 | AC12: 214 | AD12: 94 | AE12: 28 | AF12: 25 | AG12: 155 | AH12: 8 | AI12: 10 | AJ12: 1 | AK12: 17 | AL12: 4 | AM12: 14 | AN12: 7 | AO12: 10 | AP12: 9 | AQ12: 7 | AR12: 2 | AS12: 5 | AT12: 0 | AU12: 2 | AV12: 1 | AW12: 0 | AX12: 0 | AY12: 0 | AZ12: 0 | BA12: 0 | BB12: 0 | BC12: 0 | BD12: 0 | BE12: 0 | BF12: 0 | BG12: 5.95
A13: 79321 | B13: CHILLI LIGHTS | C13: =IF(A13="","",IFERROR(INDEX(Assumptions!$B$41:$B$55,MATCH(TRUE(),INDEX(ISNUMBER(SEARCH(" "&Assumptions!$A$41:$A$55&" "," "&SUBSTITUTE(SUBSTITUTE(SUBSTITUTE(SUBSTITUTE(B13,"-"," "),","," "),"/"," "),"."," ")&" ")),0),0)),"Other")) -> Lighting | D13: =IF(A13="","",BG13*(1-Assumptions!$B$18)) -> 3.45 | E13: =IF(A13="","",INDEX(Assumptions!$B$23:$B$26,MOD(VALUE(LEFT(A13,5)),4)+1)) -> 4 | F13: 2900 | G13: 337 | H13: 589 | I13: 60 | J13: 0 | K13: 933 | L13: 175 | M13: 165 | N13: 105 | O13: 99 | P13: 192 | Q13: 305 | R13: 75 | S13: 39 | T13: 270 | U13: 108 | V13: 22 | W13: 85 | X13: 14 | Y13: 5 | Z13: 4 | AA13: 5 | AB13: 109 | AC13: 187 | AD13: 44 | AE13: 72 | AF13: 27 | AG13: 95 | AH13: 113 | AI13: 60 | AJ13: 113 | AK13: 23 | AL13: 33 | AM13: 133 | AN13: 651 | AO13: 87 | AP13: 135 | AQ13: 62 | AR13: 110 | AS13: 210 | AT13: 71 | AU13: 262 | AV13: 28 | AW13: 162 | AX13: 51 | AY13: 150 | AZ13: 109 | BA13: 431 | BB13: 166 | BC13: 482 | BD13: 389 | BE13: 959 | BF13: 314 | BG13: 5.75
A14: 22197 | B14: POPCORN HOLDER | C14: =IF(A14="","",IFERROR(INDEX(Assumptions!$B$41:$B$55,MATCH(TRUE(),INDEX(ISNUMBER(SEARCH(" "&Assumptions!$A$41:$A$55&" "," "&SUBSTITUTE(SUBSTITUTE(SUBSTITUTE(SUBSTITUTE(B14,"-"," "),","," "),"/"," "),"."," ")&" ")),0),0)),"Other")) -> Other | D14: =IF(A14="","",BG14*(1-Assumptions!$B$18)) -> 0.51 | E14: =IF(A14="","",INDEX(Assumptions!$B$23:$B$26,MOD(VALUE(LEFT(A14,5)),4)+1)) -> 4 | F14: 5997 | G14: 1012 | H14: 981 | I14: 252 | J14: 0 | K14: 807 | L14: 344 | M14: 261 | N14: 351 | O14: 107 | P14: 239 | Q14: 1040 | R14: 1312 | S14: 370 | T14: 779 | U14: 583 | V14: 237 | W14: 1042 | X14: 564 | Y14: 784 | Z14: 232 | AA14: 310 | AB14: 372 | AC14: 381 | AD14: 1300 | AE14: 4562 | AF14: 533 | AG14: 410 | AH14: 437 | AI14: 345 | AJ14: 430 | AK14: 636 | AL14: 157 | AM14: 621 | AN14: 436 | AO14: 2178 | AP14: 1735 | AQ14: 518 | AR14: 826 | AS14: 956 | AT14: 516 | AU14: 570 | AV14: 682 | AW14: 1675 | AX14: 835 | AY14: 884 | AZ14: 1164 | BA14: 2775 | BB14: 1156 | BC14: 3900 | BD14: 3145 | BE14: 2955 | BF14: 3275 | BG14: 0.85
A15: 23298 | B15: SPOTTY BUNTING | C15: =IF(A15="","",IFERROR(INDEX(Assumptions!$B$41:$B$55,MATCH(TRUE(),INDEX(ISNUMBER(SEARCH(" "&Assumptions!$A$41:$A$55&" "," "&SUBSTITUTE(SUBSTITUTE(SUBSTITUTE(SUBSTITUTE(B15,"-"," "),","," "),"/"," "),"."," ")&" ")),0),0)),"Other")) -> Other | D15: =IF(A15="","",BG15*(1-Assumptions!$B$18)) -> 2.97 | E15: =IF(A15="","",INDEX(Assumptions!$B$23:$B$26,MOD(VALUE(LEFT(A15,5)),4)+1)) -> 6 | F15: 4189 | G15: 0 | H15: 0 | I15: 0 | J15: 0 | K15: 0 | L15: 0 | M15: 0 | N15: 0 | O15: 0 | P15: 0 | Q15: 0 | R15: 0 | S15: 0 | T15: 0 | U15: 0 | V15: 0 | W15: 0 | X15: 0 | Y15: 0 | Z15: 0 | AA15: 0 | AB15: 378 | AC15: 464 | AD15: 602 | AE15: 220 | AF15: 273 | AG15: 310 | AH15: 328 | AI15: 220 | AJ15: 195 | AK15: 383 | AL15: 229 | AM15: 662 | AN15: 161 | AO15: 251 | AP15: 249 | AQ15: 539 | AR15: 397 | AS15: 164 | AT15: 139 | AU15: 127 | AV15: 314 | AW15: 313 | AX15: 173 | AY15: 153 | AZ15: 106 | BA15: 89 | BB15: 103 | BC15: 129 | BD15: 136 | BE15: 458 | BF15: 112 | BG15: 4.95
A16: 22386 | B16: JUMBO BAG PINK POLKADOT | C16: =IF(A16="","",IFERROR(INDEX(Assumptions!$B$41:$B$55,MATCH(TRUE(),INDEX(ISNUMBER(SEARCH(" "&Assumptions!$A$41:$A$55&" "," "&SUBSTITUTE(SUBSTITUTE(SUBSTITUTE(SUBSTITUTE(B16,"-"," "),","," "),"/"," "),"."," ")&" ")),0),0)),"Other")) -> Bags | D16: =IF(A16="","",BG16*(1-Assumptions!$B$18)) -> 1.248 | E16: =IF(A16="","",INDEX(Assumptions!$B$23:$B$26,MOD(VALUE(LEFT(A16,5)),4)+1)) -> 6 | F16: 4088 | G16: 270 | H16: 107 | I16: 9 | J16: 0 | K16: 543 | L16: 323 | M16: 73 | N16: 199 | O16: 225 | P16: 95 | Q16: 409 | R16: 260 | S16: 174 | T16: 374 | U16: 1083 | V16: 586 | W16: 675 | X16: 125 | Y16: 119 | Z16: 155 | AA16: 282 | AB16: 154 | AC16: 401 | AD16: 179 | AE16: 560 | AF16: 410 | AG16: 478 | AH16: 243 | AI16: 611 | AJ16: 456 | AK16: 454 | AL16: 315 | AM16: 307 | AN16: 403 | AO16: 382 | AP16: 551 | AQ16: 586 | AR16: 619 | AS16: 248 | AT16: 657 | AU16: 478 | AV16: 809 | AW16: 665 | AX16: 1649 | AY16: 437 | AZ16: 334 | BA16: 743 | BB16: 313 | BC16: 516 | BD16: 522 | BE16: 253 | BF16: 436 | BG16: 2.08
A17: 23203 | B17: JUMBO BAG VINTAGE DOILY | C17: =IF(A17="","",IFERROR(INDEX(Assumptions!$B$41:$B$55,MATCH(TRUE(),INDEX(ISNUMBER(SEARCH(" "&Assumptions!$A$41:$A$55&" "," "&SUBSTITUTE(SUBSTITUTE(SUBSTITUTE(SUBSTITUTE(B17,"-"," "),","," "),"/"," "),"."," ")&" ")),0),0)),"Other")) -> Bags | D17: =IF(A17="","",BG17*(1-Assumptions!$B$18)) -> 1.248 | E17: =IF(A17="","",INDEX(Assumptions!$B$23:$B$26,MOD(VALUE(LEFT(A17,5)),4)+1)) -> 8 | F17: 2304 | G17: 0 | H17: 0 | I17: 0 | J17: 0 | K17: 0 | L17: 0 | M17: 0 | N17: 0 | O17: 0 | P17: 0 | Q17: 0 | R17: 0 | S17: 0 | T17: 0 | U17: 0 | V17: 0 | W17: 0 | X17: 0 | Y17: 0 | Z17: 0 | AA17: 0 | AB17: 120 | AC17: 908 | AD17: 1047 | AE17: 347 | AF17: 467 | AG17: 244 | AH17: 780 | AI17: 304 | AJ17: 258 | AK17: 375 | AL17: 441 | AM17: 773 | AN17: 593 | AO17: 1211 | AP17: 1308 | AQ17: 726 | AR17: 611 | AS17: 460 | AT17: 523 | AU17: 695 | AV17: 774 | AW17: 570 | AX17: 1041 | AY17: 424 | AZ17: 219 | BA17: 556 | BB17: 495 | BC17: 1714 | BD17: 1122 | BE17: 530 | BF17: 336 | BG17: 2.08
... A504: 23531 | B504: WALL ART BIG LOVE | C504: =IF(A504="","",IFERROR(INDEX(Assumptions!$B$41:$B$55,MATCH(TRUE(),INDEX(ISNUMBER(SEARCH(" "&Assumptions!$A$41:$A$55&" "," "&SUBSTITUTE(SUBSTITUTE(SUBSTITUTE(SUBSTITUTE(B504,"-"," "),","," "),"/"," "),"."," ")&" ")),0),0)),"Other")) -> Other | D504: =IF(A504="","",BG504*(1-Assumptions!$B$18)) -> 4.17 | E504: =IF(A504="","",INDEX(Assumptions!$B$23:$B$26,MOD(VALUE(LEFT(A504,5)),4)+1)) -> 8 | F504: 48 | G504: 0 | H504: 0 | I504: 0 | J504: 0 | K504: 0 | L504: 0 | M504: 0 | N504: 0 | O504: 0 | P504: 0 | Q504: 0 | R504: 0 | S504: 0 | T504: 0 | U504: 0 | V504: 0 | W504: 0 | X504: 0 | Y504: 0 | Z504: 0 | AA504: 0 | AB504: 0 | AC504: 0 | AD504: 0 | AE504: 0 | AF504: 0 | AG504: 0 | AH504: 0 | AI504: 0 | AJ504: 0 | AK504: 0 | AL504: 0 | AM504: 0 | AN504: 0 | AO504: 0 | AP504: 0 | AQ504: 0 | AR504: 0 | AS504: 0 | AT504: 0 | AU504: 0 | AV504: 0 | AW504: 0 | AX504: 256 | AY504: 32 | AZ504: 162 | BA504: 67 | BB504: 172 | BC504: 49 | BD504: 14 | BE504: 29 | BF504: 51 | BG504: 6.95

Sheet SKU_Policy
A1: SKU_Policy — stocking policy per SKU (all formulas)
A2: Green = pulled from another tab · Black = calculated here · Grey headers = helper columns. Safety stock and reorder point are rounded UP to whole units; EOQ rounded to nearest unit. Unit Cost, Lead Time and On Hand are ASSUMPTIONS / SIMULATED (see Assumptions tab).
A4: SKU | B4: Category | C4: Unit Cost (£) ASSUMPTION | D4: Lead Time (wks) SIMULATED + shock | E4: On Hand (simulated) | F4: Annual Demand (units) | G4: Avg Weekly Demand | H4: Std Dev Weekly Demand | I4: CV | J4: Annual Consumption Value (£) | K4: Value Share % | L4: Cumulative Value Share % | M4: ABC Class | N4: XYZ Class | O4: ABC-XYZ | P4: Target Service Level | Q4: Z-Score | R4: Safety Stock (units) | S4: Reorder Point (units) | T4: EOQ (units) | U4: Safety Stock Value (£) | V4: On Hand Value (£) | W4: Weeks of Cover | X4: Max Stock threshold (ROP + EOQ) | Y4: Excess Units | Z4: Excess Value (£) | AA4: Stock Status | AB4: Value Rank (helper) | AC4: Description (helper) | AD4: Std Dev × √LT (helper) | AE4: Std Dev × √LT × Unit Cost (helper) | AF4: Value rounded to 0.01 for ranking (helper — avoids floating-point tie errors)
A5: =IF(Weekly_Demand!A5="","",Weekly_Demand!A5) -> 22423 | B5: =IF($A5="","",Weekly_Demand!C5) -> Kitchen | C5: =IF($A5="","",Weekly_Demand!D5) -> 7.65 | D5: =IF($A5="","",Weekly_Demand!E5+Assumptions!$B$19) -> 8 | E5: =IF($A5="","",Weekly_Demand!F5) -> 743 | F5: =IF($A5="","",SUM(Weekly_Demand!G5:BF5)) -> 12881 | G5: =IF($A5="","",IFERROR(F5/Assumptions!$B$6,0)) -> 247.71154 | H5: =IF($A5="","",STDEV(Weekly_Demand!G5:BF5)) -> 126.39548 | I5: =IF($A5="","",IFERROR(H5/G5,0)) -> 0.51025269 | J5: =IF($A5="","",F5*C5) -> 98539.65 | K5: =IF($A5="","",IFERROR(J5/$J$505,0)) -> 0.025497368 | L5: =IF($A5="","",IFERROR(SUMIFS($J$5:$J$504,$AB$5:$AB$504,"<="&AB5)/$J$505,0)) -> 0.025497368 | M5: =IF($A5="","",IF(L5<=Assumptions!$B$7,"A",IF(L5<=Assumptions!$B$8,"B","C"))) -> A | N5: =IF($A5="","",IF(I5<=Assumptions!$B$9,"X",IF(I5<=Assumptions!$B$10,"Y","Z"))) -> Y | O5: =IF($A5="","",M5&N5) -> AY | P5: =IF($A5="","",INDEX(Assumptions!$B$35:$B$37,MATCH(M5,Assumptions!$A$35:$A$37,0))) -> 0.98 | Q5: =IF($A5="","",NORMSINV(P5)) -> 2.0537489 | R5: =IF($A5="","",ROUNDUP(Q5*H5*SQRT(D5),0)) -> 735 | S5: =IF($A5="","",ROUNDUP(G5*D5+R5,0)) -> 2717 | T5: =IF($A5="","",IFERROR(ROUND(SQRT(2*F5*Assumptions!$B$4/(Assumptions!$B$5*C5)),0),0)) -> 821 | U5: =IF($A5="","",R5*C5) -> 5622.75 | V5: =IF($A5="","",E5*C5) -> 5683.95 | W5: =IF($A5="","",IFERROR(E5/G5,0)) -> 2.9994566 | X5: =IF($A5="","",S5+T5) -> 3538 | Y5: =IF($A5="","",MAX(0,E5-X5)) -> 0 | Z5: =IF($A5="","",Y5*C5) -> 0 | AA5: =IF($A5="","",IF(E5<=R5,"Below Safety Stock",IF(E5<=S5,"Reorder Now",IF(E5>X5,"Excess","Healthy")))) -> Reorder Now | AB5: =IF($A5="","",RANK(AF5,$AF$5:$AF$504,0)+COUNTIF($AF$5:AF5,AF5)-1) -> 1 | AC5: =IF($A5="","",Weekly_Demand!B5) -> REGENCY CAKESTAND 3 TIER | AD5: =IF($A5="","",H5*SQRT(D5)) -> 357.5004 | AE5: =IF($A5="","",AD5*C5) -> 2734.8781 | AF5: =IF($A5="","",ROUND(J5,2)) -> 98539.65
A6: =IF(Weekly_Demand!A6="","",Weekly_Demand!A6) -> 85123A | B6: =IF($A6="","",Weekly_Demand!C6) -> Lighting | C6: =IF($A6="","",Weekly_Demand!D6) -> 1.77 | D6: =IF($A6="","",Weekly_Demand!E6+Assumptions!$B$19) -> 8 | E6: =IF($A6="","",Weekly_Demand!F6) -> 1395 | F6: =IF($A6="","",SUM(Weekly_Demand!G6:BF6)) -> 36258 | G6: =IF($A6="","",IFERROR(F6/Assumptions!$B$6,0)) -> 697.26923 | H6: =IF($A6="","",STDEV(Weekly_Demand!G6:BF6)) -> 566.98546 | I6: =IF($A6="","",IFERROR(H6/G6,0)) -> 0.81315142 | J6: =IF($A6="","",F6*C6) -> 64176.66 | K6: =IF($A6="","",IFERROR(J6/$J$505,0)) -> 0.016605863 | L6: =IF($A6="","",IFERROR(SUMIFS($J$5:$J$504,$AB$5:$AB$504,"<="&AB6)/$J$505,0)) -> 0.04210323 | M6: =IF($A6="","",IF(L6<=Assumptions!$B$7,"A",IF(L6<=Assumptions!$B$8,"B","C"))) -> A | N6: =IF($A6="","",IF(I6<=Assumptions!$B$9,"X",IF(I6<=Assumptions!$B$10,"Y","Z"))) -> Y | O6: =IF($A6="","",M6&N6) -> AY | P6: =IF($A6="","",INDEX(Assumptions!$B$35:$B$37,MATCH(M6,Assumptions!$A$35:$A$37,0))) -> 0.98 | Q6: =IF($A6="","",NORMSINV(P6)) -> 2.0537489 | R6: =IF($A6="","",ROUNDUP(Q6*H6*SQRT(D6),0)) -> 3294 | S6: =IF($A6="","",ROUNDUP(G6*D6+R6,0)) -> 8873 | T6: =IF($A6="","",IFERROR(ROUND(SQRT(2*F6*Assumptions!$B$4/(Assumptions!$B$5*C6)),0),0)) -> 2862 | U6: =IF($A6="","",R6*C6) -> 5830.38 | V6: =IF($A6="","",E6*C6) -> 2469.15 | W6: =IF($A6="","",IFERROR(E6/G6,0)) -> 2.0006619 | X6: =IF($A6="","",S6+T6) -> 11735 | Y6: =IF($A6="","",MAX(0,E6-X6)) -> 0 | Z6: =IF($A6="","",Y6*C6) -> 0 | AA6: =IF($A6="","",IF(E6<=R6,"Below Safety Stock",IF(E6<=S6,"Reorder Now",IF(E6>X6,"Excess","Healthy")))) -> Below Safety Stock | AB6: =IF($A6="","",RANK(AF6,$AF$5:$AF$504,0)+COUNTIF($AF$5:AF6,AF6)-1) -> 2 | AC6: =IF($A6="","",Weekly_Demand!B6) -> WHITE HANGING HEART T-LIGHT HOLDER | AD6: =IF($A6="","",H6*SQRT(D6)) -> 1603.6771 | AE6: =IF($A6="","",AD6*C6) -> 2838.5084 | AF6: =IF($A6="","",ROUND(J6,2)) -> 64176.66
A7: =IF(Weekly_Demand!A7="","",Weekly_Demand!A7) -> 47566 | B7: =IF($A7="","",Weekly_Demand!C7) -> Other | C7: =IF($A7="","",Weekly_Demand!D7) -> 2.97 | D7: =IF($A7="","",Weekly_Demand!E7+Assumptions!$B$19) -> 6 | E7: =IF($A7="","",Weekly_Demand!F7) -> 14706 | F7: =IF($A7="","",SUM(Weekly_Demand!G7:BF7)) -> 18207 | G7: =IF($A7="","",IFERROR(F7/Assumptions!$B$6,0)) -> 350.13462 | H7: =IF($A7="","",STDEV(Weekly_Demand!G7:BF7)) -> 251.72332 | I7: =IF($A7="","",IFERROR(H7/G7,0)) -> 0.71893297 | J7: =IF($A7="","",F7*C7) -> 54074.79 | K7: =IF($A7="","",IFERROR(J7/$J$505,0)) -> 0.01399198 | L7: =IF($A7="","",IFERROR(SUMIFS($J$5:$J$504,$AB$5:$AB$504,"<="&AB7)/$J$505,0)) -> 0.071379476 | M7: =IF($A7="","",IF(L7<=Assumptions!$B$7,"A",IF(L7<=Assumptions!$B$8,"B","C"))) -> A | N7: =IF($A7="","",IF(I7<=Assumptions!$B$9,"X",IF(I7<=Assumptions!$B$10,"Y","Z"))) -> Y | O7: =IF($A7="","",M7&N7) -> AY | P7: =IF($A7="","",INDEX(Assumptions!$B$35:$B$37,MATCH(M7,Assumptions!$A$35:$A$37,0))) -> 0.98 | Q7: =IF($A7="","",NORMSINV(P7)) -> 2.0537489 | R7: =IF($A7="","",ROUNDUP(Q7*H7*SQRT(D7),0)) -> 1267 | S7: =IF($A7="","",ROUNDUP(G7*D7+R7,0)) -> 3368 | T7: =IF($A7="","",IFERROR(ROUND(SQRT(2*F7*Assumptions!$B$4/(Assumptions!$B$5*C7)),0),0)) -> 1566 | U7: =IF($A7="","",R7*C7) -> 3762.99 | V7: =IF($A7="","",E7*C7) -> 43676.82 | W7: =IF($A7="","",IFERROR(E7/G7,0)) -> 42.000989 | X7: =IF($A7="","",S7+T7) -> 4934 | Y7: =IF($A7="","",MAX(0,E7-X7)) -> 9772 | Z7: =IF($A7="","",Y7*C7) -> 29022.84 | AA7: =IF($A7="","",IF(E7<=R7,"Below Safety Stock",IF(E7<=S7,"Reorder Now",IF(E7>X7,"Excess","Healthy")))) -> Excess | AB7: =IF($A7="","",RANK(AF7,$AF$5:$AF$504,0)+COUNTIF($AF$5:AF7,AF7)-1) -> 4 | AC7: =IF($A7="","",Weekly_Demand!B7) -> PARTY BUNTING | AD7: =IF($A7="","",H7*SQRT(D7)) -> 616.59368 | AE7: =IF($A7="","",AD7*C7) -> 1831.2832 | AF7: =IF($A7="","",ROUND(J7,2)) -> 54074.79
A8: =IF(Weekly_Demand!A8="","",Weekly_Demand!A8) -> 85099B | B8: =IF($A8="","",Weekly_Demand!C8) -> Bags | C8: =IF($A8="","",Weekly_Demand!D8) -> 1.248 | D8: =IF($A8="","",Weekly_Demand!E8+Assumptions!$B$19) -> 8 | E8: =IF($A8="","",Weekly_Demand!F8) -> 11833 | F8: =IF($A8="","",SUM(Weekly_Demand!G8:BF8)) -> 47331 | G8: =IF($A8="","",IFERROR(F8/Assumptions!$B$6,0)) -> 910.21154 | H8: =IF($A8="","",STDEV(Weekly_Demand!G8:BF8)) -> 500.0586 | I8: =IF($A8="","",IFERROR(H8/G8,0)) -> 0.54938723 | J8: =IF($A8="","",F8*C8) -> 59069.088 | K8: =IF($A8="","",IFERROR(J8/$J$505,0)) -> 0.015284266 | L8: =IF($A8="","",IFERROR(SUMIFS($J$5:$J$504,$AB$5:$AB$504,"<="&AB8)/$J$505,0)) -> 0.057387497 | M8: =IF($A8="","",IF(L8<=Assumptions!$B$7,"A",IF(L8<=Assumptions!$B$8,"B","C"))) -> A | N8: =IF($A8="","",IF(I8<=Assumptions!$B$9,"X",IF(I8<=Assumptions!$B$10,"Y","Z"))) -> Y | O8: =IF($A8="","",M8&N8) -> AY | P8: =IF($A8="","",INDEX(Assumptions!$B$35:$B$37,MATCH(M8,Assumptions!$A$35:$A$37,0))) -> 0.98 | Q8: =IF($A8="","",NORMSINV(P8)) -> 2.0537489 | R8: =IF($A8="","",ROUNDUP(Q8*H8*SQRT(D8),0)) -> 2905 | S8: =IF($A8="","",ROUNDUP(G8*D8+R8,0)) -> 10187 | T8: =IF($A8="","",IFERROR(ROUND(SQRT(2*F8*Assumptions!$B$4/(Assumptions!$B$5*C8)),0),0)) -> 3895 | U8: =IF($A8="","",R8*C8) -> 3625.44 | V8: =IF($A8="","",E8*C8) -> 14767.584 | W8: =IF($A8="","",IFERROR(E8/G8,0)) -> 13.000275 | X8: =IF($A8="","",S8+T8) -> 14082 | Y8: =IF($A8="","",MAX(0,E8-X8)) -> 0 | Z8: =IF($A8="","",Y8*C8) -> 0 | AA8: =IF($A8="","",IF(E8<=R8,"Below Safety Stock",IF(E8<=S8,"Reorder Now",IF(E8>X8,"Excess","Healthy")))) -> Healthy | AB8: =IF($A8="","",RANK(AF8,$AF$5:$AF$504,0)+COUNTIF($AF$5:AF8,AF8)-1) -> 3 | AC8: =IF($A8="","",Weekly_Demand!B8) -> JUMBO BAG RED RETROSPOT | AD8: =IF($A8="","",H8*SQRT(D8)) -> 1414.3793 | AE8: =IF($A8="","",AD8*C8) -> 1765.1454 | AF8: =IF($A8="","",ROUND(J8,2)) -> 59069.09
A9: =IF(Weekly_Demand!A9="","",Weekly_Demand!A9) -> 23084 | B9: =IF($A9="","",Weekly_Demand!C9) -> Lighting | C9: =IF($A9="","",Weekly_Demand!D9) -> 1.248 | D9: =IF($A9="","",Weekly_Demand!E9+Assumptions!$B$19) -> 2 | E9: =IF($A9="","",Weekly_Demand!F9) -> 7426 | F9: =IF($A9="","",SUM(Weekly_Demand!G9:BF9)) -> 27583 | G9: =IF($A9="","",IFERROR(F9/Assumptions!$B$6,0)) -> 530.44231 | H9: =IF($A9="","",STDEV(Weekly_Demand!G9:BF9)) -> 1236.0178 | I9: =IF($A9="","",IFERROR(H9/G9,0)) -> 2.3301644 | J9: =IF($A9="","",F9*C9) -> 34423.584 | K9: =IF($A9="","",IFERROR(J9/$J$505,0)) -> 0.0089071838 | L9: =IF($A9="","",IFERROR(SUMIFS($J$5:$J$504,$AB$5:$AB$504,"<="&AB9)/$J$505,0)) -> 0.089439609 | M9: =IF($A9="","",IF(L9<=Assumptions!$B$7,"A",IF(L9<=Assumptions!$B$8,"B","C"))) -> A | N9: =IF($A9="","",IF(I9<=Assumptions!$B$9,"X",IF(I9<=Assumptions!$B$10,"Y","Z"))) -> Z | O9: =IF($A9="","",M9&N9) -> AZ | P9: =IF($A9="","",INDEX(Assumptions!$B$35:$B$37,MATCH(M9,Assumptions!$A$35:$A$37,0))) -> 0.98 | Q9: =IF($A9="","",NORMSINV(P9)) -> 2.0537489 | R9: =IF($A9="","",ROUNDUP(Q9*H9*SQRT(D9),0)) -> 3590 | S9: =IF($A9="","",ROUNDUP(G9*D9+R9,0)) -> 4651 | T9: =IF($A9="","",IFERROR(ROUND(SQRT(2*F9*Assumptions!$B$4/(Assumptions!$B$5*C9)),0),0)) -> 2973 | U9: =IF($A9="","",R9*C9) -> 4480.32 | V9: =IF($A9="","",E9*C9) -> 9267.648 | W9: =IF($A9="","",IFERROR(E9/G9,0)) -> 13.999637 | X9: =IF($A9="","",S9+T9) -> 7624 | Y9: =IF($A9="","",MAX(0,E9-X9)) -> 0 | Z9: =IF($A9="","",Y9*C9) -> 0 | AA9: =IF($A9="","",IF(E9<=R9,"Below Safety Stock",IF(E9<=S9,"Reorder Now",IF(E9>X9,"Excess","Healthy")))) -> Healthy | AB9: =IF($A9="","",RANK(AF9,$AF$5:$AF$504,0)+COUNTIF($AF$5:AF9,AF9)-1) -> 6 | AC9: =IF($A9="","",Weekly_Demand!B9) -> RABBIT NIGHT LIGHT | AD9: =IF($A9="","",H9*SQRT(D9)) -> 1747.9931 | AE9: =IF($A9="","",AD9*C9) -> 2181.4954 | AF9: =IF($A9="","",ROUND(J9,2)) -> 34423.58
A10: =IF(Weekly_Demand!A10="","",Weekly_Demand!A10) -> 22086 | B10: =IF($A10="","",Weekly_Demand!C10) -> Other | C10: =IF($A10="","",Weekly_Demand!D10) -> 1.77 | D10: =IF($A10="","",Weekly_Demand!E10+Assumptions!$B$19) -> 6 | E10: =IF($A10="","",Weekly_Demand!F10) -> 3304 | F10: =IF($A10="","",SUM(Weekly_Demand!G10:BF10)) -> 17180 | G10: =IF($A10="","",IFERROR(F10/Assumptions!$B$6,0)) -> 330.38462 | H10: =IF($A10="","",STDEV(Weekly_Demand!G10:BF10)) -> 544.36659 | I10: =IF($A10="","",IFERROR(H10/G10,0)) -> 1.6476754 | J10: =IF($A10="","",F10*C10) -> 30408.6 | K10: =IF($A10="","",IFERROR(J10/$J$505,0)) -> 0.0078682972 | L10: =IF($A10="","",IFERROR(SUMIFS($J$5:$J$504,$AB$5:$AB$504,"<="&AB10)/$J$505,0)) -> 0.10572156 | M10: =IF($A10="","",IF(L10<=Assumptions!$B$7,"A",IF(L10<=Assumptions!$B$8,"B","C"))) -> A | N10: =IF($A10="","",IF(I10<=Assumptions!$B$9,"X",IF(I10<=Assumptions!$B$10,"Y","Z"))) -> Z | O10: =IF($A10="","",M10&N10) -> AZ | P10: =IF($A10="","",INDEX(Assumptions!$B$35:$B$37,MATCH(M10,Assumptions!$A$35:$A$37,0))) -> 0.98 | Q10: =IF($A10="","",NORMSINV(P10)) -> 2.0537489 | R10: =IF($A10="","",ROUNDUP(Q10*H10*SQRT(D10),0)) -> 2739 | S10: =IF($A10="","",ROUNDUP(G10*D10+R10,0)) -> 4722 | T10: =IF($A10="","",IFERROR(ROUND(SQRT(2*F10*Assumptions!$B$4/(Assumptions!$B$5*C10)),0),0)) -> 1970 | U10: =IF($A10="","",R10*C10) -> 4848.03 | V10: =IF($A10="","",E10*C10) -> 5848.08 | W10: =IF($A10="","",IFERROR(E10/G10,0)) -> 10.000466 | X10: =IF($A10="","",S10+T10) -> 6692 | Y10: =IF($A10="","",MAX(0,E10-X10)) -> 0 | Z10: =IF($A10="","",Y10*C10) -> 0 | AA10: =IF($A10="","",IF(E10<=R10,"Below Safety Stock",IF(E10<=S10,"Reorder Now",IF(E10>X10,"Excess","Healthy")))) -> Reorder Now | AB10: =IF($A10="","",RANK(AF10,$AF$5:$AF$504,0)+COUNTIF($AF$5:AF10,AF10)-1) -> 8 | AC10: =IF($A10="","",Weekly_Demand!B10) -> PAPER CHAIN KIT 50'S CHRISTMAS | AD10: =IF($A10="","",H10*SQRT(D10)) -> 1333.4204 | AE10: =IF($A10="","",AD10*C10) -> 2360.1541 | AF10: =IF($A10="","",ROUND(J10,2)) -> 30408.6
A11: =IF(Weekly_Demand!A11="","",Weekly_Demand!A11) -> 84879 | B11: =IF($A11="","",Weekly_Demand!C11) -> Other | C11: =IF($A11="","",Weekly_Demand!D11) -> 1.014 | D11: =IF($A11="","",Weekly_Demand!E11+Assumptions!$B$19) -> 8 | E11: =IF($A11="","",Weekly_Demand!F11) -> 33543 | F11: =IF($A11="","",SUM(Weekly_Demand!G11:BF11)) -> 34885 | G11: =IF($A11="","",IFERROR(F11/Assumptions!$B$6,0)) -> 670.86538 | H11: =IF($A11="","",STDEV(Weekly_Demand!G11:BF11)) -> 560.65186 | I11: =IF($A11="","",IFERROR(H11/G11,0)) -> 0.8357144 | J11: =IF($A11="","",F11*C11) -> 35373.39 | K11: =IF($A11="","",IFERROR(J11/$J$505,0)) -> 0.0091529484 | L11: =IF($A11="","",IFERROR(SUMIFS($J$5:$J$504,$AB$5:$AB$504,"<="&AB11)/$J$505,0)) -> 0.080532425 | M11: =IF($A11="","",IF(L11<=Assumptions!$B$7,"A",IF(L11<=Assumptions!$B$8,"B","C"))) -> A | N11: =IF($A11="","",IF(I11<=Assumptions!$B$9,"X",IF(I11<=Assumptions!$B$10,"Y","Z"))) -> Y | O11: =IF($A11="","",M11&N11) -> AY | P11: =IF($A11="","",INDEX(Assumptions!$B$35:$B$37,MATCH(M11,Assumptions!$A$35:$A$37,0))) -> 0.98 | Q11: =IF($A11="","",NORMSINV(P11)) -> 2.0537489 | R11: =IF($A11="","",ROUNDUP(Q11*H11*SQRT(D11),0)) -> 3257 | S11: =IF($A11="","",ROUNDUP(G11*D11+R11,0)) -> 8624 | T11: =IF($A11="","",IFERROR(ROUND(SQRT(2*F11*Assumptions!$B$4/(Assumptions!$B$5*C11)),0),0)) -> 3710 | U11: =IF($A11="","",R11*C11) -> 3302.598 | V11: =IF($A11="","",E11*C11) -> 34012.602 | W11: =IF($A11="","",IFERROR(E11/G11,0)) -> 49.999599 | X11: =IF($A11="","",S11+T11) -> 12334 | Y11: =IF($A11="","",MAX(0,E11-X11)) -> 21209 | Z11: =IF($A11="","",Y11*C11) -> 21505.926 | AA11: =IF($A11="","",IF(E11<=R11,"Below Safety Stock",IF(E11<=S11,"Reorder Now",IF(E11>X11,"Excess","Healthy")))) -> Excess | AB11: =IF($A11="","",RANK(AF11,$AF$5:$AF$504,0)+COUNTIF($AF$5:AF11,AF11)-1) -> 5 | AC11: =IF($A11="","",Weekly_Demand!B11) -> ASSORTED COLOUR BIRD ORNAMENT | AD11: =IF($A11="","",H11*SQRT(D11)) -> 1585.7629 | AE11: =IF($A11="","",AD11*C11) -> 1607.9636 | AF11: =IF($A11="","",ROUND(J11,2)) -> 35373.39
A12: =IF(Weekly_Demand!A12="","",Weekly_Demand!A12) -> 22502 | B12: =IF($A12="","",Weekly_Demand!C12) -> Other | C12: =IF($A12="","",Weekly_Demand!D12) -> 3.57 | D12: =IF($A12="","",Weekly_Demand!E12+Assumptions!$B$19) -> 6 | E12: =IF($A12="","",Weekly_Demand!F12) -> 468 | F12: =IF($A12="","",SUM(Weekly_Demand!G12:BF12)) -> 1873 | G12: =IF($A12="","",IFERROR(F12/Assumptions!$B$6,0)) -> 36.019231 | H12: =IF($A12="","",STDEV(Weekly_Demand!G12:BF12)) -> 49.690213 | I12: =IF($A12="","",IFERROR(H12/G12,0)) -> 1.3795468 | J12: =IF($A12="","",F12*C12) -> 6686.61 | K12: =IF($A12="","",IFERROR(J12/$J$505,0)) -> 0.0017301762 | L12: =IF($A12="","",IFERROR(SUMIFS($J$5:$J$504,$AB$5:$AB$504,"<="&AB12)/$J$505,0)) -> 0.65569821 | M12: =IF($A12="","",IF(L12<=Assumptions!$B$7,"A",IF(L12<=Assumptions!$B$8,"B","C"))) -> A | N12: =IF($A12="","",IF(I12<=Assumptions!$B$9,"X",IF(I12<=Assumptions!$B$10,"Y","Z"))) -> Z | O12: =IF($A12="","",M12&N12) -> AZ | P12: =IF($A12="","",INDEX(Assumptions!$B$35:$B$37,MATCH(M12,Assumptions!$A$35:$A$37,0))) -> 0.98 | Q12: =IF($A12="","",NORMSINV(P12)) -> 2.0537489 | R12: =IF($A12="","",ROUNDUP(Q12*H12*SQRT(D12),0)) -> 250 | S12: =IF($A12="","",ROUNDUP(G12*D12+R12,0)) -> 467 | T12: =IF($A12="","",IFERROR(ROUND(SQRT(2*F12*Assumptions!$B$4/(Assumptions!$B$5*C12)),0),0)) -> 458 | U12: =IF($A12="","",R12*C12) -> 892.5 | V12: =IF($A12="","",E12*C12) -> 1670.76 | W12: =IF($A12="","",IFERROR(E12/G12,0)) -> 12.993059 | X12: =IF($A12="","",S12+T12) -> 925 | Y12: =IF($A12="","",MAX(0,E12-X12)) -> 0 | Z12: =IF($A12="","",Y12*C12) -> 0 | AA12: =IF($A12="","",IF(E12<=R12,"Below Safety Stock",IF(E12<=S12,"Reorder Now",IF(E12>X12,"Excess","Healthy")))) -> Healthy | AB12: =IF($A12="","",RANK(AF12,$AF$5:$AF$504,0)+COUNTIF($AF$5:AF12,AF12)-1) -> 189 | AC12: =IF($A12="","",Weekly_Demand!B12) -> PICNIC BASKET WICKER SMALL | AD12: =IF($A12="","",H12*SQRT(D12)) -> 121.71567 | AE12: =IF($A12="","",AD12*C12) -> 434.52493 | AF12: =IF($A12="","",ROUND(J12,2)) -> 6686.61
A13: =IF(Weekly_Demand!A13="","",Weekly_Demand!A13) -> 79321 | B13: =IF($A13="","",Weekly_Demand!C13) -> Lighting | C13: =IF($A13="","",Weekly_Demand!D13) -> 3.45 | D13: =IF($A13="","",Weekly_Demand!E13+Assumptions!$B$19) -> 4 | E13: =IF($A13="","",Weekly_Demand!F13) -> 2900 | F13: =IF($A13="","",SUM(Weekly_Demand!G13:BF13)) -> 9425 | G13: =IF($A13="","",IFERROR(F13/Assumptions!$B$6,0)) -> 181.25 | H13: =IF($A13="","",STDEV(Weekly_Demand!G13:BF13)) -> 212.79124 | I13: =IF($A13="","",IFERROR(H13/G13,0)) -> 1.1740206 | J13: =IF($A13="","",F13*C13) -> 32516.25 | K13: =IF($A13="","",IFERROR(J13/$J$505,0)) -> 0.0084136566 | L13: =IF($A13="","",IFERROR(SUMIFS($J$5:$J$504,$AB$5:$AB$504,"<="&AB13)/$J$505,0)) -> 0.097853265 | M13: =IF($A13="","",IF(L13<=Assumptions!$B$7,"A",IF(L13<=Assumptions!$B$8,"B","C"))) -> A | N13: =IF($A13="","",IF(I13<=Assumptions!$B$9,"X",IF(I13<=Assumptions!$B$10,"Y","Z"))) -> Z | O13: =IF($A13="","",M13&N13) -> AZ | P13: =IF($A13="","",INDEX(Assumptions!$B$35:$B$37,MATCH(M13,Assumptions!$A$35:$A$37,0))) -> 0.98 | Q13: =IF($A13="","",NORMSINV(P13)) -> 2.0537489 | R13: =IF($A13="","",ROUNDUP(Q13*H13*SQRT(D13),0)) -> 875 | S13: =IF($A13="","",ROUNDUP(G13*D13+R13,0)) -> 1600 | T13: =IF($A13="","",IFERROR(ROUND(SQRT(2*F13*Assumptions!$B$4/(Assumptions!$B$5*C13)),0),0)) -> 1045 | U13: =IF($A13="","",R13*C13) -> 3018.75 | V13: =IF($A13="","",E13*C13) -> 10005 | W13: =IF($A13="","",IFERROR(E13/G13,0)) -> 16 | X13: =IF($A13="","",S13+T13) -> 2645 | Y13: =IF($A13="","",MAX(0,E13-X13)) -> 255 | Z13: =IF($A13="","",Y13*C13) -> 879.75 | AA13: =IF($A13="","",IF(E13<=R13,"Below Safety Stock",IF(E13<=S13,"Reorder Now",IF(E13>X13,"Excess","Healthy")))) -> Excess | AB13: =IF($A13="","",RANK(AF13,$AF$5:$AF$504,0)+COUNTIF($AF$5:AF13,AF13)-1) -> 7 | AC13: =IF($A13="","",Weekly_Demand!B13) -> CHILLI LIGHTS | AD13: =IF($A13="","",H13*SQRT(D13)) -> 425.58248 | AE13: =IF($A13="","",AD13*C13) -> 1468.2596 | AF13: =IF($A13="","",ROUND(J13,2)) -> 32516.25
A14: =IF(Weekly_Demand!A14="","",Weekly_Demand!A14) -> 22197 | B14: =IF($A14="","",Weekly_Demand!C14) -> Other | C14: =IF($A14="","",Weekly_Demand!D14) -> 0.51 | D14: =IF($A14="","",Weekly_Demand!E14+Assumptions!$B$19) -> 4 | E14: =IF($A14="","",Weekly_Demand!F14) -> 5997 | F14: =IF($A14="","",SUM(Weekly_Demand!G14:BF14)) -> 51972 | G14: =IF($A14="","",IFERROR(F14/Assumptions!$B$6,0)) -> 999.46154 | H14: =IF($A14="","",STDEV(Weekly_Demand!G14:BF14)) -> 1008.7225 | I14: =IF($A14="","",IFERROR(H14/G14,0)) -> 1.0092659 | J14: =IF($A14="","",F14*C14) -> 26505.72 | K14: =IF($A14="","",IFERROR(J14/$J$505,0)) -> 0.0068584178 | L14: =IF($A14="","",IFERROR(SUMIFS($J$5:$J$504,$AB$5:$AB$504,"<="&AB14)/$J$505,0)) -> 0.12640117 | M14: =IF($A14="","",IF(L14<=Assumptions!$B$7,"A",IF(L14<=Assumptions!$B$8,"B","C"))) -> A | N14: =IF($A14="","",IF(I14<=Assumptions!$B$9,"X",IF(I14<=Assumptions!$B$10,"Y","Z"))) -> Z | O14: =IF($A14="","",M14&N14) -> AZ | P14: =IF($A14="","",INDEX(Assumptions!$B$35:$B$37,MATCH(M14,Assumptions!$A$35:$A$37,0))) -> 0.98 | Q14: =IF($A14="","",NORMSINV(P14)) -> 2.0537489 | R14: =IF($A14="","",ROUNDUP(Q14*H14*SQRT(D14),0)) -> 4144 | S14: =IF($A14="","",ROUNDUP(G14*D14+R14,0)) -> 8142 | T14: =IF($A14="","",IFERROR(ROUND(SQRT(2*F14*Assumptions!$B$4/(Assumptions!$B$5*C14)),0),0)) -> 6385 | U14: =IF($A14="","",R14*C14) -> 2113.44 | V14: =IF($A14="","",E14*C14) -> 3058.47 | W14: =IF($A14="","",IFERROR(E14/G14,0)) -> 6.0002309 | X14: =IF($A14="","",S14+T14) -> 14527 | Y14: =IF($A14="","",MAX(0,E14-X14)) -> 0 | Z14: =IF($A14="","",Y14*C14) -> 0 | AA14: =IF($A14="","",IF(E14<=R14,"Below Safety Stock",IF(E14<=S14,"Reorder Now",IF(E14>X14,"Excess","Healthy")))) -> Reorder Now | AB14: =IF($A14="","",RANK(AF14,$AF$5:$AF$504,0)+COUNTIF($AF$5:AF14,AF14)-1) -> 11 | AC14: =IF($A14="","",Weekly_Demand!B14) -> POPCORN HOLDER | AD14: =IF($A14="","",H14*SQRT(D14)) -> 2017.4449 | AE14: =IF($A14="","",AD14*C14) -> 1028.8969 | AF14: =IF($A14="","",ROUND(J14,2)) -> 26505.72
A15: =IF(Weekly_Demand!A15="","",Weekly_Demand!A15) -> 23298 | B15: =IF($A15="","",Weekly_Demand!C15) -> Other | C15: =IF($A15="","",Weekly_Demand!D15) -> 2.97 | D15: =IF($A15="","",Weekly_Demand!E15+Assumptions!$B$19) -> 6 | E15: =IF($A15="","",Weekly_Demand!F15) -> 4189 | F15: =IF($A15="","",SUM(Weekly_Demand!G15:BF15)) -> 8377 | G15: =IF($A15="","",IFERROR(F15/Assumptions!$B$6,0)) -> 161.09615 | H15: =IF($A15="","",STDEV(Weekly_Demand!G15:BF15)) -> 178.22692 | I15: =IF($A15="","",IFERROR(H15/G15,0)) -> 1.1063387 | J15: =IF($A15="","",F15*C15) -> 24879.69 | K15: =IF($A15="","",IFERROR(J15/$J$505,0)) -> 0.0064376787 | L15: =IF($A15="","",IFERROR(SUMIFS($J$5:$J$504,$AB$5:$AB$504,"<="&AB15)/$J$505,0)) -> 0.14591248 | M15: =IF($A15="","",IF(L15<=Assumptions!$B$7,"A",IF(L15<=Assumptions!$B$8,"B","C"))) -> A | N15: =IF($A15="","",IF(I15<=Assumptions!$B$9,"X",IF(I15<=Assumptions!$B$10,"Y","Z"))) -> Z | O15: =IF($A15="","",M15&N15) -> AZ | P15: =IF($A15="","",INDEX(Assumptions!$B$35:$B$37,MATCH(M15,Assumptions!$A$35:$A$37,0))) -> 0.98 | Q15: =IF($A15="","",NORMSINV(P15)) -> 2.0537489 | R15: =IF($A15="","",ROUNDUP(Q15*H15*SQRT(D15),0)) -> 897 | S15: =IF($A15="","",ROUNDUP(G15*D15+R15,0)) -> 1864 | T15: =IF($A15="","",IFERROR(ROUND(SQRT(2*F15*Assumptions!$B$4/(Assumptions!$B$5*C15)),0),0)) -> 1062 | U15: =IF($A15="","",R15*C15) -> 2664.09 | V15: =IF($A15="","",E15*C15) -> 12441.33 | W15: =IF($A15="","",IFERROR(E15/G15,0)) -> 26.003104 | X15: =IF($A15="","",S15+T15) -> 2926 | Y15: =IF($A15="","",MAX(0,E15-X15)) -> 1263 | Z15: =IF($A15="","",Y15*C15) -> 3751.11 | AA15: =IF($A15="","",IF(E15<=R15,"Below Safety Stock",IF(E15<=S15,"Reorder Now",IF(E15>X15,"Excess","Healthy")))) -> Excess | AB15: =IF($A15="","",RANK(AF15,$AF$5:$AF$504,0)+COUNTIF($AF$5:AF15,AF15)-1) -> 14 | AC15: =IF($A15="","",Weekly_Demand!B15) -> SPOTTY BUNTING | AD15: =IF($A15="","",H15*SQRT(D15)) -> 436.565 | AE15: =IF($A15="","",AD15*C15) -> 1296.5981 | AF15: =IF($A15="","",ROUND(J15,2)) -> 24879.69
A16: =IF(Weekly_Demand!A16="","",Weekly_Demand!A16) -> 22386 | B16: =IF($A16="","",Weekly_Demand!C16) -> Bags | C16: =IF($A16="","",Weekly_Demand!D16) -> 1.248 | D16: =IF($A16="","",Weekly_Demand!E16+Assumptions!$B$19) -> 6 | E16: =IF($A16="","",Weekly_Demand!F16) -> 4088 | F16: =IF($A16="","",SUM(Weekly_Demand!G16:BF16)) -> 21255 | G16: =IF($A16="","",IFERROR(F16/Assumptions!$B$6,0)) -> 408.75 | H16: =IF($A16="","",STDEV(Weekly_Demand!G16:BF16)) -> 280.0051 | I16: =IF($A16="","",IFERROR(H16/G16,0)) -> 0.68502778 | J16: =IF($A16="","",F16*C16) -> 26526.24 | K16: =IF($A16="","",IFERROR(J16/$J$505,0)) -> 0.0068637274 | L16: =IF($A16="","",IFERROR(SUMIFS($J$5:$J$504,$AB$5:$AB$504,"<="&AB16)/$J$505,0)) -> 0.11954275 | M16: =IF($A16="","",IF(L16<=Assumptions!$B$7,"A",IF(L16<=Assumptions!$B$8,"B","C"))) -> A | N16: =IF($A16="","",IF(I16<=Assumptions!$B$9,"X",IF(I16<=Assumptions!$B$10,"Y","Z"))) -> Y | O16: =IF($A16="","",M16&N16) -> AY | P16: =IF($A16="","",INDEX(Assumptions!$B$35:$B$37,MATCH(M16,Assumptions!$A$35:$A$37,0))) -> 0.98 | Q16: =IF($A16="","",NORMSINV(P16)) -> 2.0537489 | R16: =IF($A16="","",ROUNDUP(Q16*H16*SQRT(D16),0)) -> 1409 | S16: =IF($A16="","",ROUNDUP(G16*D16+R16,0)) -> 3862 | T16: =IF($A16="","",IFERROR(ROUND(SQRT(2*F16*Assumptions!$B$4/(Assumptions!$B$5*C16)),0),0)) -> 2610 | U16: =IF($A16="","",R16*C16) -> 1758.432 | V16: =IF($A16="","",E16*C16) -> 5101.824 | W16: =IF($A16="","",IFERROR(E16/G16,0)) -> 10.001223 | X16: =IF($A16="","",S16+T16) -> 6472 | Y16: =IF($A16="","",MAX(0,E16-X16)) -> 0 | Z16: =IF($A16="","",Y16*C16) -> 0 | AA16: =IF($A16="","",IF(E16<=R16,"Below Safety Stock",IF(E16<=S16,"Reorder Now",IF(E16>X16,"Excess","Healthy")))) -> Healthy | AB16: =IF($A16="","",RANK(AF16,$AF$5:$AF$504,0)+COUNTIF($AF$5:AF16,AF16)-1) -> 10 | AC16: =IF($A16="","",Weekly_Demand!B16) -> JUMBO BAG PINK POLKADOT | AD16: =IF($A16="","",H16*SQRT(D16)) -> 685.86963 | AE16: =IF($A16="","",AD16*C16) -> 855.9653 | AF16: =IF($A16="","",ROUND(J16,2)) -> 26526.24
... A504: =IF(Weekly_Demand!A504="","",Weekly_Demand!A504) -> 23531 | B504: =IF($A504="","",Weekly_Demand!C504) -> Other | C504: =IF($A504="","",Weekly_Demand!D504) -> 4.17 | D504: =IF($A504="","",Weekly_Demand!E504+Assumptions!$B$19) -> 8 | E504: =IF($A504="","",Weekly_Demand!F504) -> 48 | F504: =IF($A504="","",SUM(Weekly_Demand!G504:BF504)) -> 832 | G504: =IF($A504="","",IFERROR(F504/Assumptions!$B$6,0)) -> 16 | H504: =IF($A504="","",STDEV(Weekly_Demand!G504:BF504)) -> 48.427022 | I504: =IF($A504="","",IFERROR(H504/G504,0)) -> 3.0266889 | J504: =IF($A504="","",F504*C504) -> 3469.44 | K504: =IF($A504="","",IFERROR(J504/$J$505,0)) -> 0.00089772581 | L504: =IF($A504="","",IFERROR(SUMIFS($J$5:$J$504,$AB$5:$AB$504,"<="&AB504)/$J$505,0)) -> 0.9287014 | M504: =IF($A504="","",IF(L504<=Assumptions!$B$7,"A",IF(L504<=Assumptions!$B$8,"B","C"))) -> B | N504: =IF($A504="","",IF(I504<=Assumptions!$B$9,"X",IF(I504<=Assumptions!$B$10,"Y","Z"))) -> Z | O504: =IF($A504="","",M504&N504) -> BZ | P504: =IF($A504="","",INDEX(Assumptions!$B$35:$B$37,MATCH(M504,Assumptions!$A$35:$A$37,0))) -> 0.95 | Q504: =IF($A504="","",NORMSINV(P504)) -> 1.6448536 | R504: =IF($A504="","",ROUNDUP(Q504*H504*SQRT(D504),0)) -> 226 | S504: =IF($A504="","",ROUNDUP(G504*D504+R504,0)) -> 354 | T504: =IF($A504="","",IFERROR(ROUND(SQRT(2*F504*Assumptions!$B$4/(Assumptions!$B$5*C504)),0),0)) -> 283 | U504: =IF($A504="","",R504*C504) -> 942.42 | V504: =IF($A504="","",E504*C504) -> 200.16 | W504: =IF($A504="","",IFERROR(E504/G504,0)) -> 3 | X504: =IF($A504="","",S504+T504) -> 637 | Y504: =IF($A504="","",MAX(0,E504-X504)) -> 0 | Z504: =IF($A504="","",Y504*C504) -> 0 | AA504: =IF($A504="","",IF(E504<=R504,"Below Safety Stock",IF(E504<=S504,"Reorder Now",IF(E504>X504,"Excess","Healthy")))) -> Below Safety Stock | AB504: =IF($A504="","",RANK(AF504,$AF$5:$AF$504,0)+COUNTIF($AF$5:AF504,AF504)-1) -> 412 | AC504: =IF($A504="","",Weekly_Demand!B504) -> WALL ART BIG LOVE | AD504: =IF($A504="","",H504*SQRT(D504)) -> 136.9723 | AE504: =IF($A504="","",AD504*C504) -> 571.1745 | AF504: =IF($A504="","",ROUND(J504,2)) -> 3469.44
A505: TOTAL | J505: =SUM(J5:J504) -> 3864699 | U505: =SUM(U5:U504) -> 390415.21 | V505: =SUM(V5:V504) -> 1208878.5 | Z505: =SUM(Z5:Z504) -> 339840 | AE505: =SUM(AE5:AE504) -> 200738.79
A506: Totals row sums the £ columns. On Hand, Unit Cost and Lead Time are simulated/assumed — see Assumptions.

Sheet ABC_XYZ_Matrix
A1: ABC-XYZ Segmentation Matrix
A2: ABC = share of annual consumption value (where the money is). XYZ = coefficient of variation of weekly demand (how predictable). All counts/values are formulas on SKU_Policy.
A4: 1. SKU count per segment
A5: ABC \ XYZ | B5: X (steady) | C5: Y (variable) | D5: Z (lumpy) | E5: Total
A6: A | B6: =COUNTIFS(SKU_Policy!$M$5:$M$504,$A6,SKU_Policy!$N$5:$N$504,LEFT(B$5,1)) -> 7 | C6: =COUNTIFS(SKU_Policy!$M$5:$M$504,$A6,SKU_Policy!$N$5:$N$504,LEFT(C$5,1)) -> 116 | D6: =COUNTIFS(SKU_Policy!$M$5:$M$504,$A6,SKU_Policy!$N$5:$N$504,LEFT(D$5,1)) -> 167 | E6: =SUM(B6:D6) -> 290
A7: B | B7: =COUNTIFS(SKU_Policy!$M$5:$M$504,$A7,SKU_Policy!$N$5:$N$504,LEFT(B$5,1)) -> 0 | C7: =COUNTIFS(SKU_Policy!$M$5:$M$504,$A7,SKU_Policy!$N$5:$N$504,LEFT(C$5,1)) -> 47 | D7: =COUNTIFS(SKU_Policy!$M$5:$M$504,$A7,SKU_Policy!$N$5:$N$504,LEFT(D$5,1)) -> 99 | E7: =SUM(B7:D7) -> 146
A8: C | B8: =COUNTIFS(SKU_Policy!$M$5:$M$504,$A8,SKU_Policy!$N$5:$N$504,LEFT(B$5,1)) -> 0 | C8: =COUNTIFS(SKU_Policy!$M$5:$M$504,$A8,SKU_Policy!$N$5:$N$504,LEFT(C$5,1)) -> 25 | D8: =COUNTIFS(SKU_Policy!$M$5:$M$504,$A8,SKU_Policy!$N$5:$N$504,LEFT(D$5,1)) -> 39 | E8: =SUM(B8:D8) -> 64
A9: Total | B9: =SUM(B6:B8) -> 7 | C9: =SUM(C6:C8) -> 188 | D9: =SUM(D6:D8) -> 305 | E9: =SUM(E6:E8) -> 500
A11: 2. Annual consumption value (£) per segment
A12: ABC \ XYZ | B12: X (steady) | C12: Y (variable) | D12: Z (lumpy) | E12: Total
A13: A | B13: =SUMIFS(SKU_Policy!$J$5:$J$504,SKU_Policy!$M$5:$M$504,$A13,SKU_Policy!$N$5:$N$504,LEFT(B$12,1)) -> 91994.436 | C13: =SUMIFS(SKU_Policy!$J$5:$J$504,SKU_Policy!$M$5:$M$504,$A13,SKU_Policy!$N$5:$N$504,LEFT(C$12,1)) -> 1332839.9 | D13: =SUMIFS(SKU_Policy!$J$5:$J$504,SKU_Policy!$M$5:$M$504,$A13,SKU_Policy!$N$5:$N$504,LEFT(D$12,1)) -> 1666364.5 | E13: =SUM(B13:D13) -> 3091198.8
A14: B | B14: =SUMIFS(SKU_Policy!$J$5:$J$504,SKU_Policy!$M$5:$M$504,$A14,SKU_Policy!$N$5:$N$504,LEFT(B$12,1)) -> 0 | C14: =SUMIFS(SKU_Policy!$J$5:$J$504,SKU_Policy!$M$5:$M$504,$A14,SKU_Policy!$N$5:$N$504,LEFT(C$12,1)) -> 188123.32 | D14: =SUMIFS(SKU_Policy!$J$5:$J$504,SKU_Policy!$M$5:$M$504,$A14,SKU_Policy!$N$5:$N$504,LEFT(D$12,1)) -> 390808.94 | E14: =SUM(B14:D14) -> 578932.27
A15: C | B15: =SUMIFS(SKU_Policy!$J$5:$J$504,SKU_Policy!$M$5:$M$504,$A15,SKU_Policy!$N$5:$N$504,LEFT(B$12,1)) -> 0 | C15: =SUMIFS(SKU_Policy!$J$5:$J$504,SKU_Policy!$M$5:$M$504,$A15,SKU_Policy!$N$5:$N$504,LEFT(C$12,1)) -> 75704.184 | D15: =SUMIFS(SKU_Policy!$J$5:$J$504,SKU_Policy!$M$5:$M$504,$A15,SKU_Policy!$N$5:$N$504,LEFT(D$12,1)) -> 118863.66 | E15: =SUM(B15:D15) -> 194567.84
A16: Total | B16: =SUM(B13:B15) -> 91994.436 | C16: =SUM(C13:C15) -> 1596667.4 | D16: =SUM(D13:D15) -> 2176037.1 | E16: =SUM(E13:E15) -> 3864699
A18: 3. Share of total annual consumption value
A19: ABC \ XYZ | B19: X (steady) | C19: Y (variable) | D19: Z (lumpy) | E19: Total
A20: A | B20: =IFERROR(B13/$E$16,0) -> 0.023803778 | C20: =IFERROR(C13/$E$16,0) -> 0.34487547 | D20: =IFERROR(D13/$E$16,0) -> 0.43117577 | E20: =IFERROR(E13/$E$16,0) -> 0.79985502
A21: B | B21: =IFERROR(B14/$E$16,0) -> 0 | C21: =IFERROR(C14/$E$16,0) -> 0.048677355 | D21: =IFERROR(D14/$E$16,0) -> 0.10112274 | E21: =IFERROR(E14/$E$16,0) -> 0.14980009
A22: C | B22: =IFERROR(B15/$E$16,0) -> 0 | C22: =IFERROR(C15/$E$16,0) -> 0.019588637 | D22: =IFERROR(D15/$E$16,0) -> 0.030756253 | E22: =IFERROR(E15/$E$16,0) -> 0.05034489
A23: Total | B23: =IFERROR(B16/$E$16,0) -> 0.023803778 | C23: =IFERROR(C16/$E$16,0) -> 0.41314146 | D23: =IFERROR(D16/$E$16,0) -> 0.56305476 | E23: =IFERROR(E16/$E$16,0) -> 1
A25: 4. Recommended inventory policy by segment
A26: Segment | B26: Profile | C26: Recommended policy
A27: AX | B27: High value, steady demand | C27: Tight, automated continuous-review replenishment (ROP/EOQ). Frequent small orders, low safety stock relative to volume, negotiate VMI or blanket POs. Review parameters monthly.
A28: AY | B28: High value, variable demand | C28: ROP with safety stock as calculated; weekly planner review of forecast vs. actual. Collaborate with key wholesale customers to see large orders early.
A29: AZ | B29: High value, unpredictable (lumpy) demand | C29: Do NOT rely on the normal-distribution safety stock alone. Manual review, make-to-order or supplier-held / consignment stock, customer order lead-time agreements for bulk orders. Highest risk if Canadian/UK import lead times lengthen.
A30: BX | B30: Medium value, steady demand | C30: Automated replenishment, periodic review (e.g. weekly), larger EOQ-based orders to cut ordering cost.
A31: BY | B31: Medium value, variable | C31: Periodic review with calculated safety stock; check seasonality (Q4 gift peak) before each season.
A32: BZ | B32: Medium value, lumpy | C32: Lower service level target or order-on-demand; pool stock with similar items; review for promotional one-offs inflating history.
A33: CX | B33: Low value, steady | C33: Simple two-bin / min-max; order infrequently in bulk — cheap to hold.
A34: CY | B34: Low value, variable | C34: Min-max with generous review period; accept lower service level.
A35: CZ | B35: Low value, lumpy | C35: Candidate to reduce range, move to make/order-to-order, or discontinue. Clear excess stock; do not hold safety stock.

Sheet Service_Level_Scenario
A1: Service_Level_Scenario — what does higher service cost?
A2: Applies ONE uniform service level to all SKUs (unlike the live policy, which differentiates A/B/C). Uses unrounded safety stock: Z × Σ(Std Dev × √Lead Time) from SKU_Policy helper columns — independent of the Assumptions service-level cells.
A4: Service Level (input) | B4: Z-Score | C4: Total Safety Stock (units) | D4: Total Safety Stock Value (£) | E4: Increase vs previous step (£) | F4: Increase vs 95% (£) | G4: Increase vs 95% (%)
A5: 0.8 | B5: =NORMSINV(A5) -> 0.84162123 | C5: =B5*SUM(SKU_Policy!$AD$5:$AD$504) -> 107769.97 | D5: =B5*SUM(SKU_Policy!$AE$5:$AE$504) -> 168946.02 | E5: =0 -> 0 | F5: =D5-$D$9 -> -161239.9 | G5: =IFERROR(D5/$D$9-1,0) -> -0.48833062
A6: 0.85 | B6: =NORMSINV(A6) -> 1.0364334 | C6: =B6*SUM(SKU_Policy!$AD$5:$AD$504) -> 132715.75 | D6: =B6*SUM(SKU_Policy!$AE$5:$AE$504) -> 208052.38 | E6: =D6-D5 -> 39106.356 | F6: =D6-$D$9 -> -122133.54 | G6: =IFERROR(D6/$D$9-1,0) -> -0.36989324
A7: 0.9 | B7: =NORMSINV(A7) -> 1.2815516 | C7: =B7*SUM(SKU_Policy!$AD$5:$AD$504) -> 164103.24 | D7: =B7*SUM(SKU_Policy!$AE$5:$AE$504) -> 257257.11 | E7: =D7-D6 -> 49204.725 | F7: =D7-$D$9 -> -72928.815 | G7: =IFERROR(D7/$D$9-1,0) -> -0.22087197
A8: 0.92 | B8: =NORMSINV(A8) -> 1.4050716 | C8: =B8*SUM(SKU_Policy!$AD$5:$AD$504) -> 179920.03 | D8: =B8*SUM(SKU_Policy!$AE$5:$AE$504) -> 282052.36 | E8: =D8-D7 -> 24795.254 | F8: =D8-$D$9 -> -48133.561 | G8: =IFERROR(D8/$D$9-1,0) -> -0.14577715
A9: 0.95 | B9: =NORMSINV(A9) -> 1.6448536 | C9: =B9*SUM(SKU_Policy!$AD$5:$AD$504) -> 210624.23 | D9: =B9*SUM(SKU_Policy!$AE$5:$AE$504) -> 330185.92 | E9: =D9-D8 -> 48133.561 | F9: =D9-$D$9 -> 0 | G9: =IFERROR(D9/$D$9-1,0) -> 0
A10: 0.97 | B10: =NORMSINV(A10) -> 1.8807936 | C10: =B10*SUM(SKU_Policy!$AD$5:$AD$504) -> 240836.45 | D10: =B10*SUM(SKU_Policy!$AE$5:$AE$504) -> 377548.23 | E10: =D10-D9 -> 47362.305 | F10: =D10-$D$9 -> 47362.305 | G10: =IFERROR(D10/$D$9-1,0) -> 0.14344132
A11: 0.98 | B11: =NORMSINV(A11) -> 2.0537489 | C11: =B11*SUM(SKU_Policy!$AD$5:$AD$504) -> 262983.45 | D11: =B11*SUM(SKU_Policy!$AE$5:$AE$504) -> 412267.06 | E11: =D11-D10 -> 34718.838 | F11: =D11-$D$9 -> 82081.143 | G11: =IFERROR(D11/$D$9-1,0) -> 0.24859068
A12: 0.99 | B12: =NORMSINV(A12) -> 2.3263479 | C12: =B12*SUM(SKU_Policy!$AD$5:$AD$504) -> 297889.87 | D12: =B12*SUM(SKU_Policy!$AE$5:$AE$504) -> 466988.25 | E12: =D12-D11 -> 54721.185 | F12: =D12-$D$9 -> 136802.33 | G12: =IFERROR(D12/$D$9-1,0) -> 0.41431908
A13: 0.995 | B13: =NORMSINV(A13) -> 2.5758293 | C13: =B13*SUM(SKU_Policy!$AD$5:$AD$504) -> 329836.07 | D13: =B13*SUM(SKU_Policy!$AE$5:$AE$504) -> 517068.85 | E13: =D13-D12 -> 50080.599 | F13: =D13-$D$9 -> 186882.93 | G13: =IFERROR(D13/$D$9-1,0) -> 0.56599302
A15: Live policy comparison (A/B/C differentiated service levels from Assumptions)
A16: Measure | C16: Units | D16: Value (£)
A17: Current policy — unrounded (Σ Z × Std Dev × √LT) | C17: =SUMPRODUCT(SKU_Policy!$Q$5:$Q$504,SKU_Policy!$AD$5:$AD$504) -> 245940.92 | D17: =SUMPRODUCT(SKU_Policy!$Q$5:$Q$504,SKU_Policy!$AE$5:$AE$504) -> 389664.05
A18: Current policy — rounded up per SKU (SKU_Policy totals) | C18: =SUM(SKU_Policy!$R$5:$R$504) -> 246195 | D18: =SKU_Policy!$U$505 -> 390415.21
A19: Rounding difference | C19: =C18-C17 -> 254.08124 | D19: =D18-D17 -> 751.15785
A20: Note on rounding: SKU_Policy rounds each SKU's safety stock UP to a whole unit (you cannot stock 0.4 of a mug), so its total is slightly higher than the unrounded totals in this scenario table — at most 1 unit × unit cost per SKU. The scenario table stays unrounded so the curve is smooth and comparable across levels.
A22: Lead-time sensitivity — supplier delay stress test (live A/B/C service levels)
A23: Why it matters: tariff changes and border/port delays lengthen supplier lead times. Safety stock grows with √LT and reorder-point stock grows linearly with LT. Unrounded; relative to the lead times currently in SKU_Policy.
A24: Extra lead time (weeks, input) | C24: Safety Stock Value (£) | D24: Increase vs +0 (£) | E24: Reorder-Point Inventory Value (£) | F24: Increase vs +0 (£) | G24: SS increase vs +0 (%)
A25: 0 | C25: =SUMPRODUCT(SKU_Policy!$Q$5:$Q$504,SKU_Policy!$H$5:$H$504,SQRT(SKU_Policy!$D$5:$D$504+A25),SKU_Policy!$C$5:$C$504) -> 389664.05 | D25: =C25-$C$25 -> 0 | E25: =SUMPRODUCT(SKU_Policy!$G$5:$G$504,SKU_Policy!$D$5:$D$504+A25,SKU_Policy!$C$5:$C$504)+C25 -> 780656.36 | F25: =E25-$E$25 -> 0 | G25: =IFERROR(C25/$C$25-1,0) -> 0
A26: 1 | C26: =SUMPRODUCT(SKU_Policy!$Q$5:$Q$504,SKU_Policy!$H$5:$H$504,SQRT(SKU_Policy!$D$5:$D$504+A26),SKU_Policy!$C$5:$C$504) -> 429793.33 | D26: =C26-$C$25 -> 40129.277 | E26: =SUMPRODUCT(SKU_Policy!$G$5:$G$504,SKU_Policy!$D$5:$D$504+A26,SKU_Policy!$C$5:$C$504)+C26 -> 895106.77 | F26: =E26-$E$25 -> 114450.41 | G26: =IFERROR(C26/$C$25-1,0) -> 0.10298429
A27: 2 | C27: =SUMPRODUCT(SKU_Policy!$Q$5:$Q$504,SKU_Policy!$H$5:$H$504,SQRT(SKU_Policy!$D$5:$D$504+A27),SKU_Policy!$C$5:$C$504) -> 465864.3 | D27: =C27-$C$25 -> 76200.25 | E27: =SUMPRODUCT(SKU_Policy!$G$5:$G$504,SKU_Policy!$D$5:$D$504+A27,SKU_Policy!$C$5:$C$504)+C27 -> 1005498.9 | F27: =E27-$E$25 -> 224842.52 | G27: =IFERROR(C27/$C$25-1,0) -> 0.19555371
A28: 3 | C28: =SUMPRODUCT(SKU_Policy!$Q$5:$Q$504,SKU_Policy!$H$5:$H$504,SQRT(SKU_Policy!$D$5:$D$504+A28),SKU_Policy!$C$5:$C$504) -> 499021.56 | D28: =C28-$C$25 -> 109357.51 | E28: =SUMPRODUCT(SKU_Policy!$G$5:$G$504,SKU_Policy!$D$5:$D$504+A28,SKU_Policy!$C$5:$C$504)+C28 -> 1112977.3 | F28: =E28-$E$25 -> 332320.91 | G28: =IFERROR(C28/$C$25-1,0) -> 0.28064562
A29: 4 | C29: =SUMPRODUCT(SKU_Policy!$Q$5:$Q$504,SKU_Policy!$H$5:$H$504,SQRT(SKU_Policy!$D$5:$D$504+A29),SKU_Policy!$C$5:$C$504) -> 529926.37 | D29: =C29-$C$25 -> 140262.32 | E29: =SUMPRODUCT(SKU_Policy!$G$5:$G$504,SKU_Policy!$D$5:$D$504+A29,SKU_Policy!$C$5:$C$504)+C29 -> 1218203.2 | F29: =E29-$E$25 -> 437546.86 | G29: =IFERROR(C29/$C$25-1,0) -> 0.35995705

Sheet Summary
A1: Summary — Inventory Health Headline KPIs
A2: Every value is a formula on other tabs. £ values at ASSUMED unit cost; On Hand is SIMULATED — interpret stock-position KPIs as a demonstration of the method.
A4: KPI | B4: Value | C4: How it is calculated
A5: SKUs analysed | B5: =SUMPRODUCT(--(SKU_Policy!$A$5:$A$504<>"")) -> 500 | C5: Count of SKU rows in SKU_Policy
A6: Annual consumption value (£) | B6: =SKU_Policy!$J$505 -> 3864699 | C6: Σ Annual Demand × Unit Cost (at cost)
A7: On-hand inventory value (£) — simulated stock | B7: =SKU_Policy!$V$505 -> 1208878.5 | C7: Σ On Hand × Unit Cost
A8: Safety stock value (£) | B8: =SKU_Policy!$U$505 -> 390415.21 | C8: Σ Safety Stock × Unit Cost (live A/B/C service levels)
A9: Excess inventory value (£) | B9: =SKU_Policy!$Z$505 -> 339840 | C9: Σ units above Reorder Point + EOQ × Unit Cost
A10: Excess as % of on-hand value | B10: =IFERROR(B9/B7,0) -> 0.28112007 | C10: Excess value ÷ On-hand value
A11: Inventory turns (annualised) | B11: =IFERROR(B6/B7,0) -> 3.1969293 | C11: Annual consumption value ÷ On-hand value
A12: Days on hand | B12: =IFERROR(Assumptions!$B$14/B11,0) -> 114.17206 | C12: Days per year (Assumptions) ÷ Turns
A13: SKUs below safety stock | B13: =COUNTIF(SKU_Policy!$AA$5:$AA$504,"Below Safety Stock") -> 108 | C13: Stock Status = Below Safety Stock
A14: SKUs to reorder now | B14: =COUNTIF(SKU_Policy!$AA$5:$AA$504,"Reorder Now") -> 107 | C14: Stock Status = Reorder Now (above SS, at/below ROP)
A15: SKUs in excess | B15: =COUNTIF(SKU_Policy!$AA$5:$AA$504,"Excess") -> 115 | C15: Stock Status = Excess
A16: A-class share of value (%) | B16: =IFERROR(SUMIF(SKU_Policy!$M$5:$M$504,"A",SKU_Policy!$J$5:$J$504)/B6,0) -> 0.79985502 | C16: Sanity check — should sit just under the A cut-off on Assumptions
A18: Supporting KPIs
A19: KPI | B19: Value | C19: How it is calculated
A20: SKUs healthy | B20: =COUNTIF(SKU_Policy!$AA$5:$AA$504,"Healthy") -> 170 | C20: Stock Status = Healthy
A21: A-class SKUs (count) | B21: =COUNTIF(SKU_Policy!$M$5:$M$504,"A") -> 290 | C21: Number of SKUs making up the A cut-off of value
A22: A-class SKUs as % of SKUs analysed | B22: =IFERROR(B21/B5,0) -> 0.58 | C22: Pareto concentration within the top-500 range
A23: A-class SKUs below safety stock | B23: =COUNTIFS(SKU_Policy!$M$5:$M$504,"A",SKU_Policy!$AA$5:$AA$504,"Below Safety Stock") -> 62 | C23: Highest stock-out risk: high value AND below buffer
A24: Z-class share of SKUs (%) | B24: =IFERROR(COUNTIF(SKU_Policy!$N$5:$N$504,"Z")/B5,0) -> 0.61 | C24: Share of SKUs with CV above the Y cut-off
A25: Cost to raise uniform service level 95% → 98% (£) | B25: =INDEX(Service_Level_Scenario!$D$5:$D$13,MATCH(0.98,Service_Level_Scenario!$A$5:$A$13,0))-INDEX(Service_Level_Scenario!$D$5:$D$13,MATCH(0.95,Service_Level_Scenario!$A$5:$A$13,0)) -> 82081.143 | C25: Service_Level_Scenario, unrounded
A26: Cost to raise uniform service level 95% → 99% (£) | B26: =INDEX(Service_Level_Scenario!$D$5:$D$13,MATCH(0.99,Service_Level_Scenario!$A$5:$A$13,0))-INDEX(Service_Level_Scenario!$D$5:$D$13,MATCH(0.95,Service_Level_Scenario!$A$5:$A$13,0)) -> 136802.33 | C26: Service_Level_Scenario, unrounded
A27: Extra safety stock value if lead times +2 weeks (£) | B27: =INDEX(Service_Level_Scenario!$D$25:$D$29,MATCH(2,Service_Level_Scenario!$A$25:$A$29,0)) -> 76200.25 | C27: Lead-time sensitivity table (supplier delay stress test)
A30: By Category (keyword rule on Description)
A31: Category | B31: SKUs | C31: Annual Consumption Value (£) | D31: On-hand Value (£) | E31: Excess Value (£) | F31: Excess % of On-hand | G31: SKUs Below Safety Stock
A32: Bags | B32: =COUNTIF(SKU_Policy!$B$5:$B$504,A32) -> 52 | C32: =SUMIFS(SKU_Policy!$J$5:$J$504,SKU_Policy!$B$5:$B$504,A32) -> 555395.15 | D32: =SUMIFS(SKU_Policy!$V$5:$V$504,SKU_Policy!$B$5:$B$504,A32) -> 198262.45 | E32: =SUMIFS(SKU_Policy!$Z$5:$Z$504,SKU_Policy!$B$5:$B$504,A32) -> 66278.4 | F32: =IFERROR(E32/D32,0) -> 0.33429628 | G32: =COUNTIFS(SKU_Policy!$B$5:$B$504,A32,SKU_Policy!$AA$5:$AA$504,"Below Safety Stock") -> 9
A33: Lighting | B33: =COUNTIF(SKU_Policy!$B$5:$B$504,A33) -> 30 | C33: =SUMIFS(SKU_Policy!$J$5:$J$504,SKU_Policy!$B$5:$B$504,A33) -> 324227.72 | D33: =SUMIFS(SKU_Policy!$V$5:$V$504,SKU_Policy!$B$5:$B$504,A33) -> 82137.348 | E33: =SUMIFS(SKU_Policy!$Z$5:$Z$504,SKU_Policy!$B$5:$B$504,A33) -> 15522.642 | F33: =IFERROR(E33/D33,0) -> 0.18898397 | G33: =COUNTIFS(SKU_Policy!$B$5:$B$504,A33,SKU_Policy!$AA$5:$AA$504,"Below Safety Stock") -> 7
A34: Kitchen | B34: =COUNTIF(SKU_Policy!$B$5:$B$504,A34) -> 46 | C34: =SUMIFS(SKU_Policy!$J$5:$J$504,SKU_Policy!$B$5:$B$504,A34) -> 408656.75 | D34: =SUMIFS(SKU_Policy!$V$5:$V$504,SKU_Policy!$B$5:$B$504,A34) -> 110792.41 | E34: =SUMIFS(SKU_Policy!$Z$5:$Z$504,SKU_Policy!$B$5:$B$504,A34) -> 31770.996 | F34: =IFERROR(E34/D34,0) -> 0.28676148 | G34: =COUNTIFS(SKU_Policy!$B$5:$B$504,A34,SKU_Policy!$AA$5:$AA$504,"Below Safety Stock") -> 7
A35: Cards/Gifts | B35: =COUNTIF(SKU_Policy!$B$5:$B$504,A35) -> 5 | C35: =SUMIFS(SKU_Policy!$J$5:$J$504,SKU_Policy!$B$5:$B$504,A35) -> 44781.654 | D35: =SUMIFS(SKU_Policy!$V$5:$V$504,SKU_Policy!$B$5:$B$504,A35) -> 10673.682 | E35: =SUMIFS(SKU_Policy!$Z$5:$Z$504,SKU_Policy!$B$5:$B$504,A35) -> 1049.07 | F35: =IFERROR(E35/D35,0) -> 0.098285671 | G35: =COUNTIFS(SKU_Policy!$B$5:$B$504,A35,SKU_Policy!$AA$5:$AA$504,"Below Safety Stock") -> 2
A36: Other | B36: =COUNTIF(SKU_Policy!$B$5:$B$504,A36) -> 367 | C36: =SUMIFS(SKU_Policy!$J$5:$J$504,SKU_Policy!$B$5:$B$504,A36) -> 2531637.7 | D36: =SUMIFS(SKU_Policy!$V$5:$V$504,SKU_Policy!$B$5:$B$504,A36) -> 807012.56 | E36: =SUMIFS(SKU_Policy!$Z$5:$Z$504,SKU_Policy!$B$5:$B$504,A36) -> 225218.89 | F36: =IFERROR(E36/D36,0) -> 0.27907731 | G36: =COUNTIFS(SKU_Policy!$B$5:$B$504,A36,SKU_Policy!$AA$5:$AA$504,"Below Safety Stock") -> 83
A37: Total | B37: =SUM(B32:B36) -> 500 | C37: =SUM(C32:C36) -> 3864699 | D37: =SUM(D32:D36) -> 1208878.5 | E37: =SUM(E32:E36) -> 339840 | F37: =IFERROR(E37/D37,0) -> 0.28112007 | G37: =SUM(G32:G36) -> 108
A38: Check: category total SKUs = SKUs analysed → | B38: =IF(B37=B5,"OK","CHECK") -> OK

Sheet Spot_Check
A1: Spot_Check — independent hand calculation vs. SKU_Policy
A2: Change the orange SKU codes to test any SKU. "Hand calc" re-derives each step directly from the raw Weekly_Demand row (INDEX/MATCH on the SKU) — it does not reuse SKU_Policy columns — then compares to the model. Diff should be 0.
A4: SKU to test → | B4: 20725 | E4: 22795 | H4: 21257
A5: Step | B5: Hand calc | C5: SKU_Policy | D5: Diff | E5: Hand calc | F5: SKU_Policy | G5: Diff | H5: Hand calc | I5: SKU_Policy | J5: Diff
A6: Description | B6: =INDEX(Weekly_Demand!$B$5:$B$504,B$7) -> LUNCH BAG RED RETROSPOT | E6: =INDEX(Weekly_Demand!$B$5:$B$504,E$7) -> SWEETHEART RECIPE BOOK STAND | H6: =INDEX(Weekly_Demand!$B$5:$B$504,H$7) -> VICTORIAN SEWING BOX MEDIUM
A7: Worksheet row (MATCH) | B7: =MATCH(B$4,Weekly_Demand!$A$5:$A$504,0) -> 17 | E7: =MATCH(E$4,Weekly_Demand!$A$5:$A$504,0) -> 279 | H7: =MATCH(H$4,Weekly_Demand!$A$5:$A$504,0) -> 385
A8: ABC-XYZ (from model) | C8: =INDEX(SKU_Policy!$O$5:$O$504,MATCH(B$4,SKU_Policy!$A$5:$A$504,0)) -> AX | F8: =INDEX(SKU_Policy!$O$5:$O$504,MATCH(E$4,SKU_Policy!$A$5:$A$504,0)) -> BY | I8: =INDEX(SKU_Policy!$O$5:$O$504,MATCH(H$4,SKU_Policy!$A$5:$A$504,0)) -> CZ
A9: Unit Cost (£) = median price × (1−margin) | B9: =INDEX(Weekly_Demand!$BG$5:$BG$504,B$7)*(1-Assumptions!$B$18) -> 0.99 | C9: =INDEX(SKU_Policy!$C$5:$C$504,MATCH(B$4,SKU_Policy!$A$5:$A$504,0)) -> 0.99 | D9: =ROUND(B9-C9,6) -> 0 | E9: =INDEX(Weekly_Demand!$BG$5:$BG$504,E$7)*(1-Assumptions!$B$18) -> 4.05 | F9: =INDEX(SKU_Policy!$C$5:$C$504,MATCH(E$4,SKU_Policy!$A$5:$A$504,0)) -> 4.05 | G9: =ROUND(E9-F9,6) -> 0 | H9: =INDEX(Weekly_Demand!$BG$5:$BG$504,H$7)*(1-Assumptions!$B$18) -> 4.77 | I9: =INDEX(SKU_Policy!$C$5:$C$504,MATCH(H$4,SKU_Policy!$A$5:$A$504,0)) -> 4.77 | J9: =ROUND(H9-I9,6) -> 0
A10: Lead Time (wks, incl. shock) | B10: =INDEX(Weekly_Demand!$E$5:$E$504,B$7)+Assumptions!$B$19 -> 4 | C10: =INDEX(SKU_Policy!$D$5:$D$504,MATCH(B$4,SKU_Policy!$A$5:$A$504,0)) -> 4 | D10: =ROUND(B10-C10,6) -> 0 | E10: =INDEX(Weekly_Demand!$E$5:$E$504,E$7)+Assumptions!$B$19 -> 8 | F10: =INDEX(SKU_Policy!$D$5:$D$504,MATCH(E$4,SKU_Policy!$A$5:$A$504,0)) -> 8 | G10: =ROUND(E10-F10,6) -> 0 | H10: =INDEX(Weekly_Demand!$E$5:$E$504,H$7)+Assumptions!$B$19 -> 4 | I10: =INDEX(SKU_Policy!$D$5:$D$504,MATCH(H$4,SKU_Policy!$A$5:$A$504,0)) -> 4 | J10: =ROUND(H10-I10,6) -> 0
A11: On Hand (simulated) | B11: =INDEX(Weekly_Demand!$F$5:$F$504,B$7) -> 19071 | C11: =INDEX(SKU_Policy!$E$5:$E$504,MATCH(B$4,SKU_Policy!$A$5:$A$504,0)) -> 19071 | D11: =ROUND(B11-C11,6) -> 0 | E11: =INDEX(Weekly_Demand!$F$5:$F$504,E$7) -> 220 | F11: =INDEX(SKU_Policy!$E$5:$E$504,MATCH(E$4,SKU_Policy!$A$5:$A$504,0)) -> 220 | G11: =ROUND(E11-F11,6) -> 0 | H11: =INDEX(Weekly_Demand!$F$5:$F$504,H$7) -> 185 | I11: =INDEX(SKU_Policy!$E$5:$E$504,MATCH(H$4,SKU_Policy!$A$5:$A$504,0)) -> 185 | J11: =ROUND(H11-I11,6) -> 0
A12: Annual Demand = Σ W1..W52 | B12: =SUM(INDEX(Weekly_Demand!$G$5:$BF$504,B$7,0)) -> 19071 | C12: =INDEX(SKU_Policy!$F$5:$F$504,MATCH(B$4,SKU_Policy!$A$5:$A$504,0)) -> 19071 | D12: =ROUND(B12-C12,6) -> 0 | E12: =SUM(INDEX(Weekly_Demand!$G$5:$BF$504,E$7,0)) -> 1145 | F12: =INDEX(SKU_Policy!$F$5:$F$504,MATCH(E$4,SKU_Policy!$A$5:$A$504,0)) -> 1145 | G12: =ROUND(E12-F12,6) -> 0 | H12: =SUM(INDEX(Weekly_Demand!$G$5:$BF$504,H$7,0)) -> 640 | I12: =INDEX(SKU_Policy!$F$5:$F$504,MATCH(H$4,SKU_Policy!$A$5:$A$504,0)) -> 640 | J12: =ROUND(H12-I12,6) -> 0
A13: Avg Weekly = Annual ÷ 52 | B13: =B12/Assumptions!$B$6 -> 366.75 | C13: =INDEX(SKU_Policy!$G$5:$G$504,MATCH(B$4,SKU_Policy!$A$5:$A$504,0)) -> 366.75 | D13: =ROUND(B13-C13,6) -> 0 | E13: =E12/Assumptions!$B$6 -> 22.019231 | F13: =INDEX(SKU_Policy!$G$5:$G$504,MATCH(E$4,SKU_Policy!$A$5:$A$504,0)) -> 22.019231 | G13: =ROUND(E13-F13,6) -> 0 | H13: =H12/Assumptions!$B$6 -> 12.307692 | I13: =INDEX(SKU_Policy!$G$5:$G$504,MATCH(H$4,SKU_Policy!$A$5:$A$504,0)) -> 12.307692 | J13: =ROUND(H13-I13,6) -> 0
A14: Std Dev Weekly (sample) | B14: =STDEV(INDEX(Weekly_Demand!$G$5:$BF$504,B$7,0)) -> 180.00859 | C14: =INDEX(SKU_Policy!$H$5:$H$504,MATCH(B$4,SKU_Policy!$A$5:$A$504,0)) -> 180.00859 | D14: =ROUND(B14-C14,6) -> 0 | E14: =STDEV(INDEX(Weekly_Demand!$G$5:$BF$504,E$7,0)) -> 21.616525 | F14: =INDEX(SKU_Policy!$H$5:$H$504,MATCH(E$4,SKU_Policy!$A$5:$A$504,0)) -> 21.616525 | G14: =ROUND(E14-F14,6) -> 0 | H14: =STDEV(INDEX(Weekly_Demand!$G$5:$BF$504,H$7,0)) -> 15.830646 | I14: =INDEX(SKU_Policy!$H$5:$H$504,MATCH(H$4,SKU_Policy!$A$5:$A$504,0)) -> 15.830646 | J14: =ROUND(H14-I14,6) -> 0
A15: CV = Std Dev ÷ Avg | B15: =B14/B13 -> 0.49082097 | C15: =INDEX(SKU_Policy!$I$5:$I$504,MATCH(B$4,SKU_Policy!$A$5:$A$504,0)) -> 0.49082097 | D15: =ROUND(B15-C15,6) -> 0 | E15: =E14/E13 -> 0.98171116 | F15: =INDEX(SKU_Policy!$I$5:$I$504,MATCH(E$4,SKU_Policy!$A$5:$A$504,0)) -> 0.98171116 | G15: =ROUND(E15-F15,6) -> 0 | H15: =H14/H13 -> 1.28624 | I15: =INDEX(SKU_Policy!$I$5:$I$504,MATCH(H$4,SKU_Policy!$A$5:$A$504,0)) -> 1.28624 | J15: =ROUND(H15-I15,6) -> 0
A16: Cumulative value share (Σ value ≥ this SKU ÷ total) | B16: =(SUMIF(SKU_Policy!$AF$5:$AF$504,">"&ROUND(B12*B9,2),SKU_Policy!$J$5:$J$504)+B12*B9)/SUM(SKU_Policy!$J$5:$J$504) -> 0.17799027 | C16: =INDEX(SKU_Policy!$L$5:$L$504,MATCH(B$4,SKU_Policy!$A$5:$A$504,0)) -> 0.17799027 | D16: =ROUND(B16-C16,6) -> 0 | E16: =(SUMIF(SKU_Policy!$AF$5:$AF$504,">"&ROUND(E12*E9,2),SKU_Policy!$J$5:$J$504)+E12*E9)/SUM(SKU_Policy!$J$5:$J$504) -> 0.80105492 | F16: =INDEX(SKU_Policy!$L$5:$L$504,MATCH(E$4,SKU_Policy!$A$5:$A$504,0)) -> 0.80105492 | G16: =ROUND(E16-F16,6) -> 0 | H16: =(SUMIF(SKU_Policy!$AF$5:$AF$504,">"&ROUND(H12*H9,2),SKU_Policy!$J$5:$J$504)+H12*H9)/SUM(SKU_Policy!$J$5:$J$504) -> 0.97600277 | I16: =INDEX(SKU_Policy!$L$5:$L$504,MATCH(H$4,SKU_Policy!$A$5:$A$504,0)) -> 0.97600277 | J16: =ROUND(H16-I16,6) -> 0
A17: ABC Class | B17: =IF(B16<=Assumptions!$B$7,"A",IF(B16<=Assumptions!$B$8,"B","C")) -> A | C17: =INDEX(SKU_Policy!$M$5:$M$504,MATCH(B$4,SKU_Policy!$A$5:$A$504,0)) -> A | D17: =IF(B17=C17,"✓","✗") -> ✓ | E17: =IF(E16<=Assumptions!$B$7,"A",IF(E16<=Assumptions!$B$8,"B","C")) -> B | F17: =INDEX(SKU_Policy!$M$5:$M$504,MATCH(E$4,SKU_Policy!$A$5:$A$504,0)) -> B | G17: =IF(E17=F17,"✓","✗") -> ✓ | H17: =IF(H16<=Assumptions!$B$7,"A",IF(H16<=Assumptions!$B$8,"B","C")) -> C | I17: =INDEX(SKU_Policy!$M$5:$M$504,MATCH(H$4,SKU_Policy!$A$5:$A$504,0)) -> C | J17: =IF(H17=I17,"✓","✗") -> ✓
A18: XYZ Class | B18: =IF(B15<=Assumptions!$B$9,"X",IF(B15<=Assumptions!$B$10,"Y","Z")) -> X | C18: =INDEX(SKU_Policy!$N$5:$N$504,MATCH(B$4,SKU_Policy!$A$5:$A$504,0)) -> X | D18: =IF(B18=C18,"✓","✗") -> ✓ | E18: =IF(E15<=Assumptions!$B$9,"X",IF(E15<=Assumptions!$B$10,"Y","Z")) -> Y | F18: =INDEX(SKU_Policy!$N$5:$N$504,MATCH(E$4,SKU_Policy!$A$5:$A$504,0)) -> Y | G18: =IF(E18=F18,"✓","✗") -> ✓ | H18: =IF(H15<=Assumptions!$B$9,"X",IF(H15<=Assumptions!$B$10,"Y","Z")) -> Z | I18: =INDEX(SKU_Policy!$N$5:$N$504,MATCH(H$4,SKU_Policy!$A$5:$A$504,0)) -> Z | J18: =IF(H18=I18,"✓","✗") -> ✓
A19: Target Service Level | B19: =IF(B17="A",Assumptions!$B$11,IF(B17="B",Assumptions!$B$12,Assumptions!$B$13)) -> 0.98 | C19: =INDEX(SKU_Policy!$P$5:$P$504,MATCH(B$4,SKU_Policy!$A$5:$A$504,0)) -> 0.98 | D19: =ROUND(B19-C19,6) -> 0 | E19: =IF(E17="A",Assumptions!$B$11,IF(E17="B",Assumptions!$B$12,Assumptions!$B$13)) -> 0.95 | F19: =INDEX(SKU_Policy!$P$5:$P$504,MATCH(E$4,SKU_Policy!$A$5:$A$504,0)) -> 0.95 | G19: =ROUND(E19-F19,6) -> 0 | H19: =IF(H17="A",Assumptions!$B$11,IF(H17="B",Assumptions!$B$12,Assumptions!$B$13)) -> 0.9 | I19: =INDEX(SKU_Policy!$P$5:$P$504,MATCH(H$4,SKU_Policy!$A$5:$A$504,0)) -> 0.9 | J19: =ROUND(H19-I19,6) -> 0
A20: Z = NORMSINV(SL) | B20: =NORMSINV(B19) -> 2.0537489 | C20: =INDEX(SKU_Policy!$Q$5:$Q$504,MATCH(B$4,SKU_Policy!$A$5:$A$504,0)) -> 2.0537489 | D20: =ROUND(B20-C20,6) -> 0 | E20: =NORMSINV(E19) -> 1.6448536 | F20: =INDEX(SKU_Policy!$Q$5:$Q$504,MATCH(E$4,SKU_Policy!$A$5:$A$504,0)) -> 1.6448536 | G20: =ROUND(E20-F20,6) -> 0 | H20: =NORMSINV(H19) -> 1.2815516 | I20: =INDEX(SKU_Policy!$Q$5:$Q$504,MATCH(H$4,SKU_Policy!$A$5:$A$504,0)) -> 1.2815516 | J20: =ROUND(H20-I20,6) -> 0
A21: Safety Stock = ROUNDUP(Z × σ × √LT) | B21: =ROUNDUP(B20*B14*SQRT(B10),0) -> 740 | C21: =INDEX(SKU_Policy!$R$5:$R$504,MATCH(B$4,SKU_Policy!$A$5:$A$504,0)) -> 740 | D21: =ROUND(B21-C21,6) -> 0 | E21: =ROUNDUP(E20*E14*SQRT(E10),0) -> 101 | F21: =INDEX(SKU_Policy!$R$5:$R$504,MATCH(E$4,SKU_Policy!$A$5:$A$504,0)) -> 101 | G21: =ROUND(E21-F21,6) -> 0 | H21: =ROUNDUP(H20*H14*SQRT(H10),0) -> 41 | I21: =INDEX(SKU_Policy!$R$5:$R$504,MATCH(H$4,SKU_Policy!$A$5:$A$504,0)) -> 41 | J21: =ROUND(H21-I21,6) -> 0
A22: Reorder Point = ROUNDUP(Avg × LT + SS) | B22: =ROUNDUP(B13*B10+B21,0) -> 2207 | C22: =INDEX(SKU_Policy!$S$5:$S$504,MATCH(B$4,SKU_Policy!$A$5:$A$504,0)) -> 2207 | D22: =ROUND(B22-C22,6) -> 0 | E22: =ROUNDUP(E13*E10+E21,0) -> 278 | F22: =INDEX(SKU_Policy!$S$5:$S$504,MATCH(E$4,SKU_Policy!$A$5:$A$504,0)) -> 278 | G22: =ROUND(E22-F22,6) -> 0 | H22: =ROUNDUP(H13*H10+H21,0) -> 91 | I22: =INDEX(SKU_Policy!$S$5:$S$504,MATCH(H$4,SKU_Policy!$A$5:$A$504,0)) -> 91 | J22: =ROUND(H22-I22,6) -> 0
A23: EOQ = ROUND(√(2 × D × S ÷ (H × C))) | B23: =ROUND(SQRT(2*B12*Assumptions!$B$4/(Assumptions!$B$5*B9)),0) -> 2776 | C23: =INDEX(SKU_Policy!$T$5:$T$504,MATCH(B$4,SKU_Policy!$A$5:$A$504,0)) -> 2776 | D23: =ROUND(B23-C23,6) -> 0 | E23: =ROUND(SQRT(2*E12*Assumptions!$B$4/(Assumptions!$B$5*E9)),0) -> 336 | F23: =INDEX(SKU_Policy!$T$5:$T$504,MATCH(E$4,SKU_Policy!$A$5:$A$504,0)) -> 336 | G23: =ROUND(E23-F23,6) -> 0 | H23: =ROUND(SQRT(2*H12*Assumptions!$B$4/(Assumptions!$B$5*H9)),0) -> 232 | I23: =INDEX(SKU_Policy!$T$5:$T$504,MATCH(H$4,SKU_Policy!$A$5:$A$504,0)) -> 232 | J23: =ROUND(H23-I23,6) -> 0
A24: Excess Units = MAX(0, On Hand − (ROP+EOQ)) | B24: =MAX(0,B11-(B22+B23)) -> 14088 | C24: =INDEX(SKU_Policy!$Y$5:$Y$504,MATCH(B$4,SKU_Policy!$A$5:$A$504,0)) -> 14088 | D24: =ROUND(B24-C24,6) -> 0 | E24: =MAX(0,E11-(E22+E23)) -> 0 | F24: =INDEX(SKU_Policy!$Y$5:$Y$504,MATCH(E$4,SKU_Policy!$A$5:$A$504,0)) -> 0 | G24: =ROUND(E24-F24,6) -> 0 | H24: =MAX(0,H11-(H22+H23)) -> 0 | I24: =INDEX(SKU_Policy!$Y$5:$Y$504,MATCH(H$4,SKU_Policy!$A$5:$A$504,0)) -> 0 | J24: =ROUND(H24-I24,6) -> 0
A25: Stock Status | B25: =IF(B11<=B21,"Below Safety Stock",IF(B11<=B22,"Reorder Now",IF(B11>B22+B23,"Excess","Healthy"))) -> Excess | C25: =INDEX(SKU_Policy!$AA$5:$AA$504,MATCH(B$4,SKU_Policy!$A$5:$A$504,0)) -> Excess | D25: =IF(B25=C25,"✓","✗") -> ✓ | E25: =IF(E11<=E21,"Below Safety Stock",IF(E11<=E22,"Reorder Now",IF(E11>E22+E23,"Excess","Healthy"))) -> Reorder Now | F25: =INDEX(SKU_Policy!$AA$5:$AA$504,MATCH(E$4,SKU_Policy!$A$5:$A$504,0)) -> Reorder Now | G25: =IF(E25=F25,"✓","✗") -> ✓ | H25: =IF(H11<=H21,"Below Safety Stock",IF(H11<=H22,"Reorder Now",IF(H11>H22+H23,"Excess","Healthy"))) -> Healthy | I25: =INDEX(SKU_Policy!$AA$5:$AA$504,MATCH(H$4,SKU_Policy!$A$5:$A$504,0)) -> Healthy | J25: =IF(H25=I25,"✓","✗") -> ✓
A27: Worked arithmetic (live text)
A28: =B4&" — "&C8&" class — "&B6 -> 20725 — AX class — LUNCH BAG RED RETROSPOT
A29: ="Safety stock: "&TEXT(B20,"0.000")&" × "&TEXT(B14,"0.00")&" × √"&B10&" = "&TEXT(B20*B14*SQRT(B10),"#,##0.00")&" → round up = "&TEXT(B21,"#,##0") -> Safety stock: 2.054 × 180.01 × √4 = 739.38 → round up = 740
A30: ="Reorder point: "&TEXT(B13,"0.00")&" × "&B10&" + "&TEXT(B21,"#,##0")&" = "&TEXT(B13*B10+B21,"#,##0.00")&" → round up = "&TEXT(B22,"#,##0")&" | EOQ: √(2 × "&TEXT(B12,"#,##0")&" × "&TEXT(Assumptions!$B$4,"0")&" ÷ ("&TEXT(Assumptions!$B$5,"0.00")&" × "&TEXT(B9,"0.000")&")) = "&TEXT(B23,"#,##0") -> Reorder point: 366.75 × 4 + 740 = 2,207.00 → round up = 2,207 | EOQ: √(2 × 19,071 × 50 ÷ (0.25 × 0.990)) = 2,776
A32: =E4&" — "&F8&" class — "&E6 -> 22795 — BY class — SWEETHEART RECIPE BOOK STAND
A33: ="Safety stock: "&TEXT(E20,"0.000")&" × "&TEXT(E14,"0.00")&" × √"&E10&" = "&TEXT(E20*E14*SQRT(E10),"#,##0.00")&" → round up = "&TEXT(E21,"#,##0") -> Safety stock: 1.645 × 21.62 × √8 = 100.57 → round up = 101
A34: ="Reorder point: "&TEXT(E13,"0.00")&" × "&E10&" + "&TEXT(E21,"#,##0")&" = "&TEXT(E13*E10+E21,"#,##0.00")&" → round up = "&TEXT(E22,"#,##0")&" | EOQ: √(2 × "&TEXT(E12,"#,##0")&" × "&TEXT(Assumptions!$B$4,"0")&" ÷ ("&TEXT(Assumptions!$B$5,"0.00")&" × "&TEXT(E9,"0.000")&")) = "&TEXT(E23,"#,##0") -> Reorder point: 22.02 × 8 + 101 = 277.15 → round up = 278 | EOQ: √(2 × 1,145 × 50 ÷ (0.25 × 4.050)) = 336
A36: =H4&" — "&I8&" class — "&H6 -> 21257 — CZ class — VICTORIAN SEWING BOX MEDIUM
A37: ="Safety stock: "&TEXT(H20,"0.000")&" × "&TEXT(H14,"0.00")&" × √"&H10&" = "&TEXT(H20*H14*SQRT(H10),"#,##0.00")&" → round up = "&TEXT(H21,"#,##0") -> Safety stock: 1.282 × 15.83 × √4 = 40.58 → round up = 41
A38: ="Reorder point: "&TEXT(H13,"0.00")&" × "&H10&" + "&TEXT(H21,"#,##0")&" = "&TEXT(H13*H10+H21,"#,##0.00")&" → round up = "&TEXT(H22,"#,##0")&" | EOQ: √(2 × "&TEXT(H12,"#,##0")&" × "&TEXT(Assumptions!$B$4,"0")&" ÷ ("&TEXT(Assumptions!$B$5,"0.00")&" × "&TEXT(H9,"0.000")&")) = "&TEXT(H23,"#,##0") -> Reorder point: 12.31 × 4 + 41 = 90.23 → round up = 91 | EOQ: √(2 × 640 × 50 ÷ (0.25 × 4.770)) = 232

Sheet Data_Prep
A1: Data_Prep — Power Query cleaning steps (ribbon clicks) and row counts
A2: Built with the Power Query Editor ribbon in Excel (Data → Get Data). Row counts are the recorded result of these steps on online_retail_II.xlsx — a static log, not formulas. Tip to see a row count at any step: Transform → Count Rows, note the number, then delete that step.
A4: # | B4: Query | C4: Action in Power Query Editor (ribbon) | D4: Settings | E4: Rows after step | F4: Why
A5: Q1 · Sales_2009_2010
A6: 1 | B6: Sales_2009_2010 | C6: Data → Get Data → From File → From Workbook → online_retail_II.xlsx → tick sheet "Year 2009-2010" → Transform Data | D6: — | E6: 525461 | F6: Raw source sheet 1 (1 Dec 2009 – 9 Dec 2010).
A7: 2 | B7: Sales_2009_2010 | C7: Applied Steps: delete "Changed Type". Select columns → Home → Data Type | D7: Invoice, StockCode, Description, Country = Text · Quantity = Whole Number · InvoiceDate = Date/Time · Price = Decimal Number · Customer ID = Whole Number | E7: 525461 | F7: Setting StockCode to Text first stops codes like 85123A turning into errors.
A8: 3 | B8: Sales_2009_2010 | C8: InvoiceDate filter arrow → Date/Time Filters → Before… | D8: before 01/12/2010 00:00 | E8: 502938 | F8: The two sheets overlap: 22,523 identical rows dated 1–9 Dec 2010 are in BOTH sheets. Keep them from sheet 2 only, or Week 1 demand is double-counted.
A9: 4 | B9: Sales_2009_2010 | C9: Home → Close & Load To… → Only Create Connection | D9: — | E9: — | F9: 1M+ rows will not fit on a worksheet (limit 1,048,576), so intermediate queries stay as connections.
A10: Q2 · Sales_2010_2011
A11: 5 | B11: Sales_2010_2011 | C11: Repeat steps 1, 2 and 4 for sheet "Year 2010-2011" (no date filter) | D11: same data types as step 2 | E11: 541910 | F11: Raw source sheet 2 (1 Dec 2010 – 9 Dec 2011).
A12: Q3 · Sales_Clean
A13: 6 | B13: Sales_Clean | C13: Data → Get Data → Combine Queries → Append → Two tables | D13: Sales_2009_2010 + Sales_2010_2011 | E13: 1044848 | F13: One combined sales table.
A14: 7 | B14: Sales_Clean | C14: Invoice filter arrow → Text Filters → Does Not Begin With… | D14: C | E14: 1025683 | F14: Invoices starting with C are cancellations/returns, not demand.
A15: 8 | B15: Sales_Clean | C15: Quantity filter arrow → Number Filters → Greater Than… | D15: 0 | E15: 1022290 | F15: Zero/negative quantities are adjustments.
A16: 9 | B16: Sales_Clean | C16: Price filter arrow → Number Filters → Greater Than… | D16: 0 | E16: 1019654 | F16: Zero-price lines are samples, damages or write-offs.
A17: 10 | B17: Sales_Clean | C17: Select StockCode → Transform → Format → Trim, then Format → UPPERCASE. Do the same Trim on Description | D17: — | E17: 1019654 | F17: So "85123a" and "85123A " become one SKU.
A18: 11 | B18: Sales_Clean | C18: Select StockCode → Add Column → Extract → First Characters → 5. Set the new column to Whole Number → Home → Remove Rows → Remove Errors → delete the helper column | D18: Count = 5 | E18: 1014945 | F18: Real products start with 5 digits. POST, DOT, M, D, C2, BANK CHARGES, AMAZONFEE etc. fail the number conversion and are removed.
A19: 12 | B19: Sales_Clean | C19: Invoice filter arrow → Text Filters → Does Not Equal… | D19: 541431 | E19: 1014944 | F19: Outlier decision: one 74,215-unit order (SKU 23166) was cancelled minutes later by C541433. Step 7 removes the cancellation but not the order, which would create false demand.
A20: 13 | B20: Sales_Clean | C20: Select InvoiceDate → Add Column → Custom Column. Name: WeekStart, then set type Date. Check with Add Column → Date → Day → Name of Day (Monday only), then delete the helper | D20: Formula: Date.StartOfWeek([InvoiceDate], Day.Monday). The ribbon Start of Week button always uses Sunday, whatever the locale | E20: 1014944 | F20: Monday of the invoice week — same idea as Excel =INT(A2)-WEEKDAY(A2,3). The only typed formula in the whole process.
A21: 14 | B21: Sales_Clean | C21: WeekStart filter arrow → Date Filters → Between… | D21: is after or equal to 06/12/2010 AND is before or equal to 28/11/2011 | E21: 500376 | F21: Exactly 52 complete Monday-starting weeks; partial weeks at either end excluded.
A22: 15 | B22: Sales_Clean | C22: Select Quantity, Ctrl+click Price → Add Column → Standard → Multiply. Rename column to LineRevenue | D22: — | E22: 500376 | F22: Revenue per invoice line.
A23: Q4 · Weekly_Sold
A24: 16 | B24: Weekly_Sold | C24: Queries pane: right-click Sales_Clean → Reference. Home → Group By → Advanced | D24: Group by StockCode, WeekStart · Units = Sum of Quantity · Revenue = Sum of LineRevenue | E24: 96033 | F24: One row per SKU per week that had sales.
A25: Q5 · Top500
A26: 17 | B26: Top500 | C26: Reference Weekly_Sold → Home → Group By | D26: Group by StockCode · Revenue52w = Sum of Revenue | E26: 3775 | F26: 3,775 distinct product SKUs in the 52 weeks.
A27: 18 | B27: Top500 | C27: Revenue52w filter arrow → Sort Descending → Home → Keep Rows → Keep Top Rows | D27: 500 | E27: 500 | F27: Workbook capacity is 500 SKUs; these are 67.5% of product revenue (£6.43M of £9.53M).
A28: Q6 · SKU_Details
A29: 19 | B29: Desc_Counts | C29: Reference Sales_Clean → Description filter: untick (null) → Home → Group By → Advanced | D29: Group by StockCode, Description · n = Count Rows | E29: — | F29: How often each description text is used per SKU.
A30: 20 | B30: Desc_Top | C30: Reference Desc_Counts → Group By StockCode, MaxN = Max of n → Home → Merge Queries with Desc_Counts (Ctrl+click StockCode then MaxN ↔ StockCode then n, Inner) → expand Description → Remove Duplicates on StockCode | D30: — | E30: 3775 | F30: Most frequent description per SKU.
A31: 21 | B31: SKU_Details | C31: Reference Sales_Clean → Home → Group By | D31: Group by StockCode · MedianPrice = Median of Price | E31: 3775 | F31: Median selling price per SKU (basis for the unit-cost assumption).
A32: 22 | B32: SKU_Details | C32: Home → Merge Queries → Desc_Top on StockCode (Left Outer) → expand Description | D32: — | E32: 3775
A33: Q7 · Weekly_Demand_Wide (loaded to a sheet)
A34: 23 | B34: Weekly_Demand_Wide | C34: Reference Weekly_Sold → Home → Merge Queries → Top500 on StockCode, Join Kind = Inner → expand Revenue52w | D34: Inner join | E34: — | F34: Keeps only the top 500 SKUs.
A35: 24 | B35: Weekly_Demand_Wide | C35: Remove the weekly Revenue column → WeekStart filter arrow → Sort Ascending → select WeekStart → Transform → Pivot Column | D35: Values Column = Units · Advanced: Aggregate = Sum | E35: 500 | F35: One row per SKU, one column per week (52 columns). Sorting first keeps weeks in date order.
A36: 25 | B36: Weekly_Demand_Wide | C36: Select all 52 week columns → Transform → Replace Values | D36: Value To Find: null · Replace With: 0 | E36: 500 | F36: ZERO-FILL: weeks with no sales must be 0, not blank. Without them the standard deviation of weekly demand is understated → safety stock is understated → false confidence in low stock.
A37: 26 | B37: Weekly_Demand_Wide | C37: Home → Merge Queries → SKU_Details on StockCode → expand Description, MedianPrice → Sort Revenue52w descending → drag columns into order → remove Revenue52w | D37: Order: StockCode, Description, 52 weeks, MedianPrice | E37: 500 | F37: Final table: 500 SKUs × 52 weeks = 26,000 SKU-weeks.
A38: 27 | B38: Weekly_Demand_Wide | C38: Home → Close & Load To… → Table → New worksheet. Then Copy → Paste Values into Weekly_Demand | D38: A:B ← StockCode, Description · G:BF ← 52 weeks · BG ← MedianPrice | E38: 500 | F38: Weekly_Demand then calculates Category, Unit Cost and Lead Time with formulas.
A40: Checks
A41: Rows removed: overlap 22,523 · cancellations 19,165 · qty ≤ 0: 3,393 · price ≤ 0: 2,636 · non-product codes 4,709 · reversed order 1 · outside 52 weeks 514,568.
A42: Final: 500 SKUs, each with exactly 52 week columns (26,000 SKU-weeks). 3,775 SKUs existed before the top-500 cut.
A43: Descriptions: if two descriptions tie on count, Remove Duplicates keeps the first one Power Query finds.
